{"Santa Clara":{"Measures":[{"pt":"0","p":"0","No":"0","Yes":"0","a":"66 2/3%","name":"Measure A","d":null},{"pt":"0","p":"0","No":"0","Yes":"0","a":"66 2/3%","name":"Measure B","d":null},{"pt":"0","p":"0","No":"0","Yes":"0","a":"50% + 1","name":"Measure C","d":null},{"pt":"0","p":"0","No":"0","Yes":"0","a":"50% + 1","name":"Measure D","d":null},{"pt":"0","p":"0","No":"0","Yes":"0","a":"50% + 1","name":"Measure E","d":null},{"pt":"0","p":"0","No":"0","Yes":"0","a":"50% + 1","name":"Measure F","d":null},{"pt":"0","p":"0","No":"0","Yes":"0","a":"50% + 1","name":"Measure G","d":null},{"pt":"0","p":"0","No":"0","Yes":"0","a":"50% + 1","name":"Measure H","d":null},{"pt":"0","p":"0","No":"0","Yes":"0","a":"50% + 1","name":"Measure I","d":null},{"pt":"0","p":"0","No":"0","Yes":"0","a":"50% + 1","name":"Measure J","d":null},{"pt":"0","p":"0","No":"0","Yes":"0","a":"50% + 1","name":"Measure K","d":null},{"pt":"0","p":"0","No":"0","Yes":"0","a":"50% + 1","name":"Measure L","d":null},{"pt":"0","p":"0","No":"0","Yes":"0","a":"50% + 1","name":"Measure M","d":null},{"pt":"0","p":"0","No":"0","Yes":"0","a":"50% + 1","name":"Measure N","d":null},{"pt":"0","p":"0","No":"0","Yes":"0","a":"50% + 1","name":"Measure O","d":null},{"pt":"0","p":"0","No":"0","Yes":"0","a":"50% + 1","name":"Measure P","d":null},{"pt":"0","p":"0","No":"0","Yes":"0","a":"50% + 1","name":"Measure Q","d":null},{"pt":"0","p":"0","No":"0","Yes":"0","a":"50% + 1","name":"Measure R","d":null},{"pt":"0","p":"0","No":"0","Yes":"0","a":"50% + 1","name":"Measure S","d":null},{"pt":"0","p":"0","No":"0","Yes":"0","a":"50% + 1","name":"Measure T","d":null},{"pt":"0","p":"0","No":"0","Yes":"0","a":"55%","name":"Measure U","d":null},{"pt":"0","p":"0","No":"0","Yes":"0","a":"50% + 1","name":"Measure V","d":null},{"pt":"0","p":"0","No":"0","Yes":"0","a":"50% + 1","name":"Measure W","d":null},{"pt":"0","p":"0","No":"0","Yes":"0","a":"55%","name":"Measure X","d":null},{"pt":"0","p":"0","No":"0","Yes":"0","a":"66 2/3%","name":"Measure Y","d":null},{"pt":"0","p":"0","No":"0","Yes":"0","a":"55%","name":"Measure Z","d":null},{"pt":"0","p":"0","No":"0","Yes":"0","a":"55%","name":"Measure AA","d":null},{"pt":"0","p":"0","No":"0","Yes":"0","a":"66 2/3%","name":"Measure BB","d":null},{"pt":"0","p":"0","No":"0","Yes":"0","a":"55%","name":"Measure CC","d":null},{"pt":"0","p":"0","No":"0","Yes":"0","a":"66 2/3%","name":"Measure EE","d":null},{"pt":"0","p":"0","No":"0","Yes":"0","a":"66 2/3%","name":"Measure GG","d":null},{"pt":"0","p":"0","No":"0","Yes":"0","a":"66 2/3%","name":"Measure HH","d":null}],"School Districts":[{"c3":"0","c1_name":"B. C. Doyle","pt":"0","c4":"0","n":"3","c2_i":1,"name":"Gilroy Unified School District Governing Board Member","c3_i":1,"c2":"0","c2_name":"James E. Pace","p":"0","c4_name":"Paul Nadeau","c3_name":"Mark W. Good","c1":"0"},{"c1_name":"Angelica Diaz","pt":"0","c2_i":1,"name":"Morgan Hill Unified School District Governing Board Member, Trustee Area 5","c2":"0","c2_name":"Thomas Arnett","p":"0","c1":"0"},{"c3":"0","c1_name":"Albert Beltran, Jr.","pt":"0","name":"Morgan Hill Unified School District Governing Board Member, Trustee Area 6","c3_i":1,"c2":"0","c2_name":"Mary Patterson","p":"0","c3_name":"Rick G. Badillo","c1":"0"},{"c3":"0","pt":"0","c4":"0","c2":"0","c5":"0","c3_name":"Jennifer Dibrienza","c6_name":"Todd Collins","c4_i":1,"c1_name":"Heidi Emberling","n":"3","c1_i":1,"name":"Palo Alto Unified School District Governing Board Member","c6":"0","c2_name":"Jay Blas Jacob Cabrera","c5_name":"Srinivasan Subramanian","p":"0","c4_name":"Melissa Baten Caswell","c1":"0"},{"c1_name":"Olivia Navarro","pt":"0","c2_i":1,"name":"San Jose Unified School District Governing Board Member, Trustee Area 3","c2":"0","c2_name":"Pam Foley","p":"0","c1":"0"},{"c1_name":"Kimberly Meek","pt":"0","c2_i":1,"name":"San Jose Unified School District Governing Board Member, Trustee Area 5","c2":"0","c2_name":"Sandra Engel","p":"0","c1":"0"},{"c3":"0","c1_name":"Albert Gonzalez","pt":"0","c1_i":1,"name":"Santa Clara Unified School District Governing Board Member, Trustee Area 2","c2":"0","c2_name":"Ashish Mangla","p":"0","c3_name":"Mark Richardson","c1":"0"},{"c1_name":"Anna E. Welsh","pt":"0","c2_i":1,"name":"Santa Clara Unified School District Governing Board Member, Trustee Area 3","c2":"0","c2_name":"Michele Ryan","p":"0","c1":"0"},{"c3":"0","pt":"0","c4":"0","c3_i":1,"c2":"0","c5":"0","c3_name":"Lan Nguyen","c6_i":1,"c6_name":"Pattie Cortese","c1_name":"Derek Grasty","n":"2","name":"East Side Union High School District Governing Board Member","c6":"0","c2_name":"Khanh Tran","c5_name":"Patricia Martinez-Roach","p":"0","c4_name":"Lorena Chavez","c1":"0"},{"c3":"0","c1_name":"Jeff Moe","pt":"0","n":"2","c1_i":1,"name":"Fremont Union High School District Governing Board Member","c2":"0","c2_name":"Jenny Yuan","p":"0","c3_name":"Roy Rocklin","c1":"0"},{"c3":"0","c1_name":"Katherine Tseng","pt":"0","c4":"0","n":"2","c1_i":1,"name":"Los Gatos-Saratoga Joint Union High School District Governing Board Member","c2":"0","c2_name":"Kyle Park","p":"0","c4_name":"Rosemary Rossi","c3_name":"Ron Jones","c1":"0","c4_i":1},{"c3":"0","pt":"0","c4":"0","c2":"0","c7":"0","c7_i":1,"c5":"0","c3_name":"Jennifer Coile","c6_name":"Patty Nehme","c7_name":"Ray Rodriguez","c1_name":"Ellen Miller","n":"2","name":"San Benito High School District Governing Board Member","c6":"0","c2_name":"F. R. Muro","c5_name":"Mary Encinias","p":"0","c4_name":"John W. Corrigan, III","c1":"0"},{"c3":"0","c1_name":"Bruce Huynh","pt":"0","n":"2","c2_i":1,"name":"Alum Rock Union School District Governing Board Member","c3_i":1,"c2":"0","c2_name":"Dolores Marquez","p":"0","c3_name":"Karen Martinez","c1":"0"},{"c3":"0","c1_name":"Gregory Anderson","pt":"0","c4":"0","n":"2","c2_i":1,"name":"Cupertino Union School District Governing Board Member","c2":"0","c2_name":"Josephine Lucey","p":"0","c4_name":"Phyllis Vogel","c3_name":"Liang-Fang Chao","c1":"0","c4_i":1},{"c3":"0","c1_name":"Bonnie Mace","pt":"0","c4":"0","n":"2","c1_i":1,"name":"Evergreen School District Governing Board Member","c2":"0","c2_name":"Leila Welch","p":"0","c4_name":"Vicente M. Songcayawon","c3_name":"Tony Qin","c1":"0","c4_i":1},{"c3":"0","c1_name":"George Sanchez","pt":"0","n":"2","c1_i":1,"c2_i":1,"name":"Franklin-McKinley SchoolDistrict Governing Board Member","c2":"0","c2_name":"John Lindner","p":"0","c3_name":"Lena Tran","c1":"0"},{"c2_name":"Tanya M. Raschke","c1_name":"Bryan Johnson","pt":"0","p":"0","name":"Los Altos School District Governing Board Member, Short Term","c2":"0","c1":"0"},{"c3":"0","c1_name":"Daniel Snyder","pt":"0","n":"2","name":"Los Gatos Union School District Governing Board Member","c2":"0","c2_name":"Mani A. Farhadi","p":"0","c3_name":"Stephen Dale Parsons","c1":"0"},{"c3":"0","c1_name":"Guadalupe Reyes","pt":"0","n":"2","c1_i":1,"name":"Luther Burbank School District Governing Board Member","c2":"0","c2_name":"Mark Lemucchi","p":"0","c3_name":"Michael Rowe","c1":"0"},{"c3":"0","c1_name":"Jose Gutierrez, Jr.","pt":"0","c4":"0","n":"3","c1_i":1,"name":"Mountain View Whisman School District Governing Board Member","c2":"0","c2_name":"Laura Blakely","p":"0","c4_name":"Tamara Wilson","c3_name":"Peter Darrah","c1":"0"},{"c3":"0","c1_name":"Antonio Perez, Jr.","pt":"0","c4":"0","n":"2","c2_i":1,"name":"Mount Pleasant School District Governing Board Member","c3_i":1,"c2":"0","c2_name":"Darrell Koide","p":"0","c4_name":"Peter Ortiz","c3_name":"Nancy F. Hopkins","c1":"0"},{"c1_name":"Andrew Nguyen Pham","pt":"0","c2_i":1,"name":"Oak Grove School District Governing Board Member, Trustee Area 1","c2":"0","c2_name":"Mary E. Noel","p":"0","c1":"0"},{"c2_name":"Steve Guerrero","c1_name":"John Mackey","pt":"0","p":"0","name":"Oak Grove School District Governing Board Member, Trustee Area 4","c2":"0","c1":"0"},{"c3":"0","c1_name":"Arati Nagaraj","pt":"0","n":"2","c1_i":1,"name":"Saratoga Union School District Governing Board Member","c2":"0","c2_name":"Rui Cao","p":"0","c3_name":"Sophia Kao","c1":"0"}],"Cities":[{"c3":"0","c1_name":"Donald C. Young","pt":"0","c4":"0","n":"2","name":"City of Campbell, City Council","c2":"0","c2_name":"Phil Reynolds","p":"0","c4_name":"Susan M. Landry","c3_name":"Rich Waterman","c1":"0"},{"c3":"0","pt":"0","c4":"0","c2":"0","c7":"0","c5":"0","c3_name":"Kris Wang","c6_i":1,"c6_name":"Rod G. Sinks","c7_name":"Steven Scharf","c1_name":"David Fung","n":"2","name":"City of Cupertino, City Council","c6":"0","c2_name":"Jerry Liu","c5_name":"Robert McCoy","p":"0","c8_name":"Val Vitols","c4_name":"Parth Bharwad","c1":"0","c8":"0"},{"c1_name":"Perry Woodward","pt":"0","c1_i":1,"name":"City of Gilroy, Mayor","c2":"0","c2_name":"Roland Velasco","p":"0","c1":"0"},{"c3":"0","pt":"0","c4":"0","c3_i":1,"c2":"0","c7":"0","c5":"0","c3_name":"Daniel Harney","c6_name":"Paul V. Kloecker","c7_name":"Reid Lerner","c1_name":"Cat Tucker","n":"3","c1_i":1,"name":"City of Gilroy, City Council","c6":"0","c2_name":"Craig Gartman","c5_name":"J Brennan","p":"0","c8_name":"Tom Fischer","c4_name":"Fred M. Tovar","c1":"0","c8":"0"},{"c3":"0","pt":"0","c4":"0","c3_i":1,"c2":"0","c5":"0","c3_name":"Jeannie Bruins","c6_name":"Steve Smiley","c1_name":"Alexander D. Glew","n":"3","name":"City of Los Altos, City Council","c2_i":1,"c6":"0","c2_name":"Jan Pepper","c5_name":"Neysa Fligor","p":"0","c4_name":"Lynette Lee Eng","c1":"0"},{"c3":"0","pt":"0","c4":"0","c2":"0","c5":"0","c3_name":"Michelle Wu","c1_name":"Courtenay C. Corrigan","n":"3","c1_i":1,"name":"Town of Los Altos Hills, City Council","c5_i":1,"c2_name":"Garo K. Kiremidjian","c5_name":"Roger Spreen","p":"0","c4_name":"Peter Evans","c1":"0"},{"c3":"0","c1_name":"Barbara Spector","pt":"0","n":"2","c1_i":1,"name":"Town of Los Gatos, Town Council","c3_i":1,"c2":"0","c2_name":"Larry Maggio","p":"0","c3_name":"Marcia Jensen","c1":"0"},{"c3":"0","c1_name":"Carmen Montano","pt":"0","c4":"0","name":"City of Milpitas, Mayor","c2":"0","c5_name":"Voltaire S. Montemayor","c2_name":"Debbie Indihar Giordano","p":"0","c5":"0","c4_name":"Robert Marini","c3_name":"Rich Tran","c1":"0"},{"c3":"0","pt":"0","c4":"0","c2":"0","c5":"0","c3_name":"Evelyn Chua","c6_name":"Mark Tiernan","c1_name":"Anthony Phan","n":"2","name":"City of Milpitas, City Council","c6":"0","c2_name":"Bob Nunez","c5_name":"Jennifer Strohfus","p":"0","c4_name":"Gwan Alisantosa","c1":"0"},{"c3":"0","c1_name":"Curtis Rogers","pt":"0","c4":"0","n":"2","c2_i":1,"name":"City of Monte Sereno, City Council","c2":"0","c2_name":"Lon Allan","p":"0","c4_name":"Rowena Turner","c3_name":"Roman Dimitrov","c1":"0"},{"c3":"0","c1_name":"Joseph Carrillo","pt":"0","name":"City of Morgan Hill, Mayor","c3_i":1,"c2":"0","c2_name":"Kirk R. Bertolet","p":"0","c3_name":"Steve Tate","c1":"0"},{"c3":"0","pt":"0","c4":"0","c3_i":1,"c2":"0","c5":"0","c3_name":"Marilyn Librers","c1_name":"Armando Benavides","n":"2","name":"City of Morgan Hill, City Council","c2_i":1,"c2_name":"Larry Carr","c5_name":"Rene A. Spring","p":"0","c4_name":"Mario Banuelos","c1":"0"},{"c1_name":"Irma Torrez","pt":"0","p":"0","c1_i":1,"name":"City of Morgan Hill, City Clerk","c1":"0"},{"c1_name":"David Clink","pt":"0","p":"0","name":"City of Morgan Hill, Treasurer","c1":"0"},{"c3":"0","pt":"0","c4":"0","c3_i":1,"c2":"0","c7":"0","c5":"0","c3_name":"John McAlister","c6_name":"Lucas Ramirez","c7_name":"Margaret Abe-Koga","c1_name":"Chris Clark","n":"4","c1_i":1,"name":"City of Mountain View, City Council","c6":"0","c2_name":"Greg Coladonato","c5_name":"Lisa Matichak","p":"0","c8_name":"Thida Cornes","c4_name":"Ken Carpenter","c1":"0","c8":"0"},{"c3":"0","pt":"0","c4":"0","c9":"0","c10":"0","c2":"0","c10_name":"Lydia Kou","c7":"0","c5":"0","c3_name":"Danielle Martell","c11_name":"Stewart Carl","c6_name":"Greg Tanaka","c7_name":"John Karl Fredrich","c1_name":"Adrian Fine","n":"4","name":"City of Palo Alto, City Council","c6":"0","c2_name":"Arthur Keller","c5_name":"Greer Stone","p":"0","c11":"0","c8_name":"Leonard W. Ely, III","c9_name":"Liz Kniss","c4_name":"Don McDougall","c9_i":1,"c1":"0","c8":"0"},{"c2_name":"Steve Brown","c1_name":"Sergio Jimenez","pt":"0","p":"0","name":"City of San Jose, City Council, District 2","c2":"0","c1":"0"},{"c2_name":"Helen K. Chapman","c1_name":"Devora Joan Davis","pt":"0","p":"0","name":"City of San Jose, City Council, District 6","c2":"0","c1":"0"},{"c2_name":"Sylvia Arenas","c1_name":"Jimmy Nguyen","pt":"0","p":"0","name":"City of San Jose, City Council, District 8","c2":"0","c1":"0"},{"c1_name":"Debi Davis","pt":"0","c1_i":1,"name":"City of Santa Clara, City Council, Seat 3","c2":"0","c2_name":"John McLemore","p":"0","c1":"0"},{"c3":"0","c1_name":"Markus A. Bracamonte","pt":"0","c4":"0","name":"City of Santa Clara, City Council, Seat 4","c2":"0","c2_name":"Patricia Mahan","p":"0","c4_name":"Tino Silva","c3_name":"Raj Chahal","c1":"0"},{"c3":"0","c1_name":"Anthony J. Becker","pt":"0","c4":"0","c2_i":1,"name":"City of Santa Clara, City Council, Seat 6","c2":"0","c5_name":"Suds Jain","c2_name":"Kathy Watanabe","p":"0","c5":"0","c4_name":"Mohammed Nadeem","c3_name":"Mario Bouza","c1":"0"},{"c3":"0","c1_name":"Ahmad Rafah","pt":"0","name":"City of Santa Clara, City Council, Seat 7","c3_i":1,"c2":"0","c2_name":"Kevin Park","p":"0","c3_name":"Teresa O'Neill","c1":"0"},{"c1_name":"Deborah Bress","pt":"0","c2_i":1,"name":"City of Santa Clara, City Clerk","c2":"0","c2_name":"Rod Diridon, Jr.","p":"0","c1":"0"},{"c1_name":"Michael J. Sellers","pt":"0","c1_i":1,"name":"City of Santa Clara, Chief of Police","c2":"0","c2_name":"Pat Nikolai","p":"0","c1":"0"},{"c3":"0","c1_name":"Dede Smullen","pt":"0","n":"2","c2_i":1,"name":"City of Saratoga, City Council","c3_i":1,"c2":"0","c2_name":"Howard Miller","p":"0","c3_name":"Manny Cappello","c1":"0"},{"c3":"0","c1_name":"John Cordes","pt":"0","name":"City of Sunnyvale, City Council, Seat 4","c2":"0","c2_name":"Larry Klein","p":"0","c3_name":"Mike McCarthy","c1":"0"},{"c1_name":"Pat Meyering","pt":"0","c1_i":1,"name":"City of Sunnyvale, City Council, Seat 5","c2":"0","c2_name":"Russ Melton","p":"0","c1":"0"},{"c1_name":"Jim Davis","pt":"0","c1_i":1,"name":"City of Sunnyvale, City Council, Seat 6","c2":"0","c2_name":"Nancy Smith","p":"0","c1":"0"},{"c3":"0","c1_name":"Michael S. Goldman","pt":"0","name":"City of Sunnyvale, City Council, Seat 7","c3_i":1,"c2":"0","c2_name":"Ron Banks","p":"0","c3_name":"Tara Martin-Milius","c1":"0"}],"County":[{"c1_name":"Grace H. Mah","pt":"0","c1_i":1,"name":"Board of Education, Trustee Area 1","c2":"0","c2_name":"Sheena Chin","p":"0","c1":"0"},{"c1_name":"Judy L. Chirco","pt":"0","c2_i":1,"name":"Board of Education, Trustee Area 3","c2":"0","c2_name":"Rosemary Kamei","p":"0","c1":"0"}],"Special Districts":[{"c1_name":"John L. Varela","pt":"0","c1_i":1,"name":"Santa Clara Valley Water District Director, District 1, Short Term","c2":"0","c2_name":"Tom Cruz","p":"0","c1":"0"},{"c3":"0","c1_name":"Angela S. Chen","pt":"0","c4":"0","n":"3","c1_i":1,"c2_i":1,"name":"Cupertino Sanitary District Director","c2":"0","c2_name":"John M. Gatto","p":"0","c4_name":"William A. Bosworth","c3_name":"Taghi Saadati","c1":"0","c4_i":1},{"c1_name":"Dorsey Moore","pt":"0","c1_i":1,"name":"Santa Clara Valley Open Space Authority Director, District 4","c2":"0","c2_name":"Pierluigi Oliverio","p":"0","c1":"0"}],"College Districts":[{"c3":"0","pt":"0","c4":"0","c3_i":1,"c2":"0","c5":"0","c3_name":"Laura Casas","c6_name":"Peter Landsberger","c1_name":"Eric Rosenthal","n":"3","name":"Foothill-De Anza Community College District Governing Board Member","c6":"0","c2_name":"Gilbert Wong","c5_name":"Patrick Ahrens","p":"0","c4_name":"Orrin Mahoney","c1":"0"},{"c2_name":"Rachel Perez","c1_name":"Danielle Davenport","pt":"0","p":"0","name":"Gavilan Joint Community College District Governing Board Member, Trustee Area 6","c2":"0","c1":"0"},{"c1_name":"Rudy Nasol","pt":"0","c1_i":1,"name":"San Jose/Evergreen Community College District Governing Board Member, Trustee Area 1","c2":"0","c2_name":"Shawn Sieu","p":"0","c1":"0"},{"c1_name":"Craig Mann","pt":"0","c1_i":1,"name":"San Jose/Evergreen Community College District Governing Board Member, Trustee Area 3","c2":"0","c2_name":"Rex Randles","p":"0","c1":"0"},{"c1_name":"Anthony Macias","pt":"0","c2_i":1,"name":"San Jose/Evergreen Community College District Governing Board Member, Trustee Area 7","c2":"0","c2_name":"Mayra Cruz","p":"0","c1":"0"},{"c1_name":"Christopher R. Stampolis","pt":"0","c2_i":1,"name":"West Valley-Mission Community College District Governing Board Member, Trustee Area 2","c2":"0","c2_name":"Robert T. Owens","p":"0","c1":"0"}]},"Contra Costa":{"Measures":[{"pt":"0","p":"0","No":"0","Yes":"0","a":"Advisory","name":"Measure A","d":null},{"pt":"0","p":"0","No":"0","Yes":"0","a":"66 2/3%","name":"Measure B","d":null},{"pt":"0","p":"0","No":"0","Yes":"0","a":"50% + 1","name":"Measure C","d":null},{"pt":"0","p":"0","No":"0","Yes":"0","a":"66 2/3%","name":"Measure D","d":null},{"pt":"0","p":"0","No":"0","Yes":"0","a":"50% + 1","name":"Measure E","d":null},{"pt":"0","p":"0","No":"0","Yes":"0","a":"Advisory","name":"Measure G","d":null},{"pt":"0","p":"0","No":"0","Yes":"0","a":"50% + 1","name":"Measure H","d":null},{"pt":"0","p":"0","No":"0","Yes":"0","a":"50% + 1","name":"Measure J","d":null},{"pt":"0","p":"0","No":"0","Yes":"0","a":"50% + 1","name":"Measure K","d":null},{"pt":"0","p":"0","No":"0","Yes":"0","a":"50% + 1","name":"Measure L","d":null},{"pt":"0","p":"0","No":"0","Yes":"0","a":"50% + 1","name":"Measure M","d":null},{"pt":"0","p":"0","No":"0","Yes":"0","a":"50% + 1","name":"Measure N","d":null},{"pt":"0","p":"0","No":"0","Yes":"0","a":"66 2/3%","name":"Measure O","d":null},{"pt":"0","p":"0","No":"0","Yes":"0","a":"55%","name":"Measure P","d":null},{"pt":"0","p":"0","No":"0","Yes":"0","a":"55%","name":"Measure Q","d":null},{"pt":"0","p":"0","No":"0","Yes":"0","a":"55%","name":"Measure R","d":null},{"pt":"0","p":"0","No":"0","Yes":"0","a":"66 2/3%","name":"Measure S","d":null},{"pt":"0","p":"0","No":"0","Yes":"0","a":"66 2/3%","name":"Measure T","d":null},{"pt":"0","p":"0","No":"0","Yes":"0","a":"55%","name":"Measure U","d":null},{"pt":"0","p":"0","No":"0","Yes":"0","a":"55%","name":"Measure V","d":null},{"pt":"0","p":"0","No":"0","Yes":"0","a":"55%","name":"Measure W","d":null},{"pt":"0","p":"0","No":"0","Yes":"0","a":"66 2/3%","name":"Measure X","d":null},{"pt":"0","p":"0","No":"0","Yes":"0","a":"50% + 1","name":"Measure Y","d":null},{"pt":"0","p":"0","No":"0","Yes":"0","a":"50% + 1","name":"Measure Z","d":null}],"School Districts":[{"c3":"0","pt":"0","c4":"0","c3_i":1,"c2":"0","c7":"0","c5":"0","c3_name":"Diane Gibson-Gray","c6_name":"Joy Motts","c7_name":"Mike Burkholder","c4_i":1,"c1_name":"Alonzo Tony Terry","n":"3","c1_i":1,"name":"Antioch Unified School District Governing Board Member","c6":"0","c2_name":"Crystal Sawyer-White","c5_name":"Gary Hack","p":"0","c4_name":"Fernando C. Navarro","c1":"0"},{"c3":"0","c1_name":"Barbara Vargen-Kotchevar","pt":"0","c4":"0","n":"3","c2_i":1,"name":"John Swett Unified School District Governing Board Member","c2":"0","c5_name":"Shane Reinhart","c2_name":"Jerrold Parsons","p":"0","c5":"0","c4_name":"Michael Joseph Hoesly","c3_name":"Marina Ramos","c1":"0"},{"c3":"0","c1_name":"Evelyn Centeno","pt":"0","c4":"0","n":"3","c2_i":1,"name":"Martinez Unified School District Governing Board Member","c3_i":1,"c2":"0","c2_name":"John L. Fuller","p":"0","c4_name":"Kathi McLaughlin","c3_name":"Jonathan T. Wright","c1":"0","c4_i":1},{"c3":"0","c1_name":"Brian Thomas Lawrence","pt":"0","c4":"0","n":"2","c1_i":1,"name":"Mt. Diablo Unified School District Governing Board Member","c2":"0","c2_name":"Cherise Marie Khaund","p":"0","c4_name":"Joanne Durkee","c3_name":"Herbert K. Lee","c1":"0"},{"c3":"0","c1_name":"George H. Miller","pt":"0","n":"2","c1_i":1,"c2_i":1,"name":"Pittsburg Unified School District Governing Board Member","c2":"0","c2_name":"Laura Canciamilla","p":"0","c3_name":"Nettie Asiasi","c1":"0"},{"c3":"0","pt":"0","c4":"0","c2":"0","c7":"0","c5":"0","c3_name":"Carlos Taboada","c6_name":"Mister Phillips","c7_name":"Tom Panas","c1_name":"Antonio Álvarez Medrano","n":"2","name":"West Contra Costa Unified School District Governing Board Member","c6":"0","c2_name":"Ayana K. Young","c5_name":"Miriam Stephanie Sequeira","p":"0","c4_name":"Don Gosney","c1":"0"},{"c3":"0","c1_name":"Daron Spears","pt":"0","c4":"0","n":"2","c2_i":1,"name":"Liberty Union High School District Governing Board Member","c2":"0","c2_name":"Raymond Valverde","p":"0","c4_name":"Yolanda C. Pena Mendrek","c3_name":"Spencer Smith","c1":"0","c4_i":1},{"c3":"0","c1_name":"David W. Turner","pt":"0","n":"2","name":"Byron Union School District Governing Board Member","c2":"0","c2_name":"Marshall Harris","p":"0","c3_name":"Susan E. Vinyard","c1":"0"},{"c3":"0","c1_name":"Janice Smith","pt":"0","c4":"0","n":"3","c1_i":1,"name":"Knightsen Elementary School District Governing Board Member","c2":"0","c2_name":"Shawndell L. McCall","p":"0","c4_name":"Thomas E. Baldocchi, Jr.","c3_name":"Stefani Provan","c1":"0","c4_i":1},{"c3":"0","c1_name":"Charles Sturm","pt":"0","n":"2","name":"Lafayette School District Governing Board Member","c2":"0","c2_name":"Mark Kindhouse","p":"0","c3_name":"Meredith Meade","c1":"0"},{"c3":"0","c1_name":"David Harrison","pt":"0","n":"2","name":"Moraga School District Governing Board Member","c2":"0","c2_name":"Joseph R. Rosenbaum","p":"0","c3_name":"Richard Severy","c1":"0"},{"c3":"0","c1_name":"Karen Bergenholtz","pt":"0","n":"2","c1_i":1,"c2_i":1,"name":"Oakley Union Elementary School District Governing Board Member","c2":"0","c2_name":"Laurence J. Polk","p":"0","c3_name":"Lisa Brizendine","c1":"0"},{"c3":"0","c1_name":"Cara Rubinstein Hoxie","pt":"0","n":"2","name":"Orinda Union School District Governing Board Member","c3_i":1,"c2":"0","c2_name":"Hillary Weiner","p":"0","c3_name":"Sarah Genn Butler","c1":"0"}],"Cities":[{"c3":"0","c1_name":"Gil Murillo","pt":"0","c4":"0","name":"City of Antioch, Mayor","c2":"0","c2_name":"Lori Ogorchock","p":"0","c4_name":"Wade Harper","c3_name":"Sean Wright","c1":"0","c4_i":1},{"c3":"0","pt":"0","c4":"0","c2":"0","c5":"0","c3_name":"Ken Turnage, II","c6_i":1,"c6_name":"Monica E. Wilson","c1_name":"Frederick Rouse","n":"2","name":"City of Antioch, City Council","c6":"0","c5_i":1,"c2_name":"Karl Dietzel","c5_name":"Mary Helen Rocha","p":"0","c4_name":"Lamar Thorpe","c1":"0"},{"c1_name":"Arne Simonsen","pt":"0","p":"0","c1_i":1,"name":"City of Antioch, City Clerk","c1":"0"},{"c1_name":"Donna Conley","pt":"0","p":"0","c1_i":1,"name":"City of Antioch, City Treasurer","c1":"0"},{"c1_name":"Robert Taylor","pt":"0","p":"0","c1_i":1,"name":"City of Brentwood, Mayor","c1":"0"},{"c3":"0","c1_name":"Claudette Staton","pt":"0","c4":"0","n":"2","name":"City of Brentwood, City Council","c2":"0","c5_name":"Robert Rodgers","c2_name":"John D. Fink","p":"0","c5":"0","c4_name":"Mark Stoiber","c3_name":"Karen Rarey","c1":"0"},{"c3":"0","c1_name":"Allen Lampo","pt":"0","c4":"0","n":"3","c2_i":1,"name":"City of Clayton, City Council","c3_i":1,"c2":"0","c2_name":"Jim Diaz","p":"0","c4_name":"Tuija Catalano","c3_name":"Julie Pierce","c1":"0"},{"c3":"0","pt":"0","c4":"0","c2":"0","c7":"0","c5":"0","c3_name":"Eduardo G. Manuel","c6_name":"Hope Johnson","c7_name":"Pablo Benavente","c1_name":"Carlyn Obringer","n":"2","name":"City of Concord, City Council","c2_i":1,"c6":"0","c2_name":"Ed Birsan","c5_name":"Harmesh Kumar","p":"0","c4_name":"Gloria Casillas","c1":"0"},{"c3":"0","c1_name":"Greg Lyman","pt":"0","c4":"0","n":"3","c1_i":1,"name":"City of El Cerrito, City Council","c2":"0","c5_name":"Rochelle Pardue-Okimoto","c2_name":"Nicholas Arzio","p":"0","c5":"0","c4_name":"Paul Fadelli","c3_name":"Parker J. Shirazi","c1":"0"},{"c3":"0","c1_name":"Alexander Brandon Walker-Griffin","pt":"0","c4":"0","n":"3","name":"City of Hercules, City Council","c3_i":1,"c2":"0","c5_name":"Roland Esquivias","c2_name":"Brian Campbell-Miller","p":"0","c5":"0","c4_name":"Gerard Boulanger","c3_name":"Dan Romero","c1":"0"},{"c3":"0","c1_name":"Cameron Burks","pt":"0","n":"3","c2_i":1,"name":"City of Lafayette, City Council","c3_i":1,"c2":"0","c2_name":"Mark J. Mitchell","p":"0","c3_name":"Mike Anderson","c1":"0"},{"c3":"0","c1_name":"Graig Crossley","pt":"0","c4":"0","n":"3","name":"Town of Moraga, Town Council","c2":"0","c2_name":"Jeanette Fritzky","p":"0","c4_name":"Roger Wykle","c3_name":"Kymberleigh Korpus","c1":"0","c4_i":1},{"c3":"0","c1_name":"Courtney Masella-O'Brien","pt":"0","c4":"0","n":"2","name":"City of Martinez, City Council","c3_i":1,"c2":"0","c2_name":"John Stevens","p":"0","c4_name":"Noralea Gipner","c3_name":"Mark Ross","c1":"0"},{"c1_name":"R. Gary Hernandez","pt":"0","p":"0","c1_i":1,"name":"City of Martinez, City Clerk","c1":"0"},{"c1_name":"Carolyn L. Robinson","pt":"0","c1_i":1,"name":"City of Martinez, City Treasurer","c2":"0","c2_name":"Charles Martin","p":"0","c1":"0"},{"c3":"0","pt":"0","c4":"0","c9":"0","c2":"0","c7":"0","c5":"0","c3_name":"Dezi Pina","c6_name":"Michael Dupray","c7_name":"Paul S. Seger","c4_i":1,"c1_name":"Bruno Korbmacher","n":"3","name":"City of Oakley, City Council","c6":"0","c5_i":1,"c2_name":"Claire Alaura","c5_name":"Kevin Romick","p":"0","c8_name":"Randi Jill Adler","c9_name":"Stephen DeMarco","c4_name":"Doug Hardcastle","c1":"0","c8":"0"},{"c3":"0","c1_name":"Bruce R. London","pt":"0","c4":"0","n":"2","c2_i":1,"name":"City of Orinda, City Council","c2":"0","c2_name":"Darlene K. Gee","p":"0","c4_name":"Linda Delehunt","c3_name":"Inga Miller","c1":"0"},{"c3":"0","c1_name":"Ben Johnson","pt":"0","c4":"0","n":"2","c1_i":1,"name":"City of Pittsburg, City Council","c2":"0","c2_name":"Jelani Killings","p":"0","c4_name":"Mark Gargalikis","c3_name":"Juan Antonio Banales","c1":"0"},{"c3":"0","c1_name":"Jonathon S. Feit","pt":"0","c4":"0","n":"3","c2_i":1,"name":"City of Pleasant Hill, City Council","c2":"0","c2_name":"Ken Carlson","p":"0","c4_name":"Tim Flaherty","c3_name":"Matthew Rinn","c1":"0","c4_i":1},{"c1_name":"Mark W. Celio","pt":"0","p":"0","c1_i":1,"name":"City of Pleasant Hill, City Treasurer","c1":"0"},{"c3":"0","pt":"0","c4":"0","c9":"0","c2":"0","c7":"0","c7_i":1,"c5":"0","c3_name":"Courtland Booze","c6_name":"Melvin Lee Willis, Jr.","c7_name":"Nathaniel Bates","c4_i":1,"c1_name":"Ben Choi","n":"3","name":"City of Richmond, City Council","c6":"0","c2_name":"Cesar Zepeda","c5_name":"Jim Rogers","p":"0","c8_name":"Uche Justin Uwahemu","c9_name":"Vinay Pimple","c4_name":"Jael Myrick","c9_i":1,"c1":"0","c8":"0"},{"c3":"0","c1_name":"Arturo Cruz","pt":"0","c4":"0","n":"3","c2_i":1,"name":"City of San Pablo, City Council","c3_i":1,"c2":"0","c2_name":"Cecilia Valdez","p":"0","c4_name":"Rich Kinney","c3_name":"Kathy Meuy Seng Chao Rothberg","c1":"0","c4_i":1},{"c1_name":"Bill Clarkson","pt":"0","p":"0","c1_i":1,"name":"City of San Ramon, Mayor","c1":"0"},{"c3":"0","c1_name":"Philip O'Loane","pt":"0","c4":"0","n":"2","c1_i":1,"name":"City of San Ramon, City Council","c3_i":1,"c2":"0","c2_name":"Sabina Zafar","p":"0","c4_name":"Susmita Nayak","c3_name":"Scott Perkins","c1":"0"},{"c3":"0","c1_name":"Bob Simmons","pt":"0","c4":"0","n":"3","c1_i":1,"c2_i":1,"name":"City of Walnut Creek, City Council","c2":"0","c2_name":"Justin Wedel","p":"0","c4_name":"Loella Haskew","c3_name":"Kevin Wilk","c1":"0","c4_i":1}],"County":[{"c3":"0","c1_name":"Elaine R. Merriweather","pt":"0","name":"Board of Education, Area 1","c3_i":1,"c2":"0","c2_name":"Fatima S. Alleyne","p":"0","c3_name":"Pam Mirabella","c1":"0"},{"c3":"0","c1_name":"Daniel A. Gomes","pt":"0","c1_i":1,"name":"Board of Education, Area 3","c2":"0","c2_name":"Leon Raymond Sloan","p":"0","c3_name":"Vikki Janeen Chavez","c1":"0"},{"c2_name":"Steve Barr","c1_name":"Diane Burgis","pt":"0","p":"0","name":"Supervisor 3rd District","c2":"0","c1":"0"},{"c1_name":"Anamarie Avila Farias","pt":"0","c2_i":1,"name":"Supervisor 5th District","c2":"0","c2_name":"Federal Glover","p":"0","c1":"0"}],"Special Districts":[{"c3":"0","c1_name":"Bill Mayer","pt":"0","c4":"0","n":"2","c2_i":1,"name":"Town of Discovery Bay, Community Services District Director","c2":"0","c2_name":"Bill Pease","p":"0","c4_name":"Mark Simon","c3_name":"Marianne B. Wiesen","c1":"0","c4_i":1},{"c3":"0","c1_name":"Chuck Toombs","pt":"0","c4":"0","n":"2","c1_i":1,"name":"Kensington Police Protection and Community Services District Director","c2":"0","c5_name":"Sylvia Hacaj","c2_name":"David P. Spath","p":"0","c5":"0","c4_name":"Simon Brafman","c3_name":"Eileen M. Nottoli","c1":"0"},{"c2_name":"Victoria Smith","c1_name":"Craig Jorgens","pt":"0","p":"0","name":"Moraga-Orinda Fire Protection District Director, Division 5","c2":"0","c1":"0"},{"c3":"0","pt":"0","c4":"0","c2":"0","c5":"0","c3_name":"Lisa Kirk","c4_i":1,"c1_name":"Anthony Joseph Berzinas","n":"3","c1_i":1,"name":"Bethel Island Municipal Improvement District Director","c2_name":"Dean Moreland","c5_name":"Torena B. Quinn","p":"0","c4_name":"Robert Amrine, Jr.","c1":"0"},{"c1_name":"Lesa R. McIntosh","pt":"0","c1_i":1,"name":"East Bay Municipal Utility District Director, Ward 1","c2":"0","c2_name":"Sarita L. Evans","p":"0","c1":"0"},{"c3":"0","c1_name":"Eva Graciela Garcia","pt":"0","c4":"0","n":"2","c1_i":1,"c2_i":1,"name":"Ambrose Recreation & Park District Director","c2":"0","c2_name":"Lee Mason","p":"0","c4_name":"Steve Hoagland","c3_name":"Marcia Lessley","c1":"0"},{"c3":"0","c1_name":"James A. Nejedly","pt":"0","c4":"0","n":"3","c1_i":1,"c2_i":1,"name":"Central Contra Costa Sanitary District Director","c2":"0","c2_name":"Paul Herbert Causey","p":"0","c4_name":"Tad J. Pilecki","c3_name":"Susan Noe Welsh","c1":"0","c4_i":1},{"c3":"0","c1_name":"Connie Batchelder","pt":"0","c4":"0","n":"3","c1_i":1,"c2_i":1,"name":"Rodeo Sanitary District Director","c3_i":1,"c2":"0","c2_name":"Janet Callaghan","p":"0","c4_name":"Terry L. Tigh","c3_name":"Richard Burke Frakes","c1":"0"},{"c3":"0","c1_name":"Burl Toler, Jr.","pt":"0","c4":"0","n":"2","name":"West County Wastewater District Director","c3_i":1,"c2":"0","c2_name":"Harry Wiener","p":"0","c4_name":"Sherry Ann Stanley","c3_name":"Michael Taylor Caine","c1":"0"},{"c2_name":"Len Battaglia","c1_name":"David Alvarado","pt":"0","p":"0","name":"West County Wastewater District Director - Short Term","c2":"0","c1":"0"},{"c1_name":"Debora Allen","pt":"0","c2_i":1,"name":"BART Board of Directors, District 1","c2":"0","c2_name":"Gail Murray","p":"0","c1":"0"},{"c1_name":"Antonio Martinez","pt":"0","c2_i":1,"name":"Contra Costa Water District Director, Division 4","c2":"0","c2_name":"Bette Boatmun","p":"0","c1":"0"}],"College Districts":[{"c1_name":"Fernando Sandoval","pt":"0","c2_i":1,"name":"Contra Costa Community College District Board Member, Ward 5","c2":"0","c2_name":"Greg Enholm","p":"0","c1":"0"}]},"San Mateo":{"Measures":[{"pt":"0","p":"0","No":"0","Yes":"0","a":"50% + 1","name":"Measure I","d":null},{"pt":"0","p":"0","No":"0","Yes":"0","a":"50% + 1","name":"Measure J","d":null},{"pt":"0","p":"0","No":"0","Yes":"0","a":"50% + 1","name":"Measure K","d":null},{"pt":"0","p":"0","No":"0","Yes":"0","a":"50% + 1","name":"Measure L","d":null},{"pt":"0","p":"0","No":"0","Yes":"0","a":"55%","name":"Measure M","d":null},{"pt":"0","p":"0","No":"0","Yes":"0","a":"66 2/3%","name":"Measure N","d":null},{"pt":"0","p":"0","No":"0","Yes":"0","a":"50% + 1","name":"Measure O","d":null},{"pt":"0","p":"0","No":"0","Yes":"0","a":"50% + 1","name":"Measure P","d":null},{"pt":"0","p":"0","No":"0","Yes":"0","a":"50% + 1","name":"Measure Q","d":null},{"pt":"0","p":"0","No":"0","Yes":"0","a":"50% + 1","name":"Measure R","d":null},{"pt":"0","p":"0","No":"0","Yes":"0","a":"55%","name":"Measure S","d":null},{"pt":"0","p":"0","No":"0","Yes":"0","a":"66 2/3%","name":"Measure T","d":null},{"pt":"0","p":"0","No":"0","Yes":"0","a":"66 2/3%","name":"Measure U","d":null},{"pt":"0","p":"0","No":"0","Yes":"0","a":"66 2/3%","name":"Measure V","d":null},{"pt":"0","p":"0","No":"0","Yes":"0","a":"50% + 1","name":"Measure W","d":null}],"School Districts":[{"c3":"0","c1_name":"Jacque McLaughlin","pt":"0","c4":"0","n":"2","name":"Brisbane School District, Governing Board Member","c2":"0","c2_name":"Lillian Markind","p":"0","c4_name":"Yakim Hayuk","c3_name":"Raul Alcaraz","c1":"0"},{"c3":"0","c1_name":"Kate Livingston","pt":"0","n":"2","c1_i":1,"name":"Cabrillo Unified School District, Governing Board Member","c2":"0","c2_name":"Kimberly K. Hines","p":"0","c3_name":"Sophia Layne","c1":"0"},{"c3":"0","c1_name":"Andrew Lie","pt":"0","n":"2","c1_i":1,"c2_i":1,"name":"Jefferson Union High School District, Governing Board Member","c2":"0","c2_name":"Kalimah Salahuddin","p":"0","c3_name":"Roberto A. Marques","c1":"0"},{"c3":"0","c1_name":"Catherine M. Perry","pt":"0","c4":"0","n":"3","name":"La Honda-Pescadero School District, Governing Board Member","c2":"0","c2_name":"Cindy Hayes","p":"0","c4_name":"Mary Windram","c3_name":"Lynne Bowman","c1":"0"},{"c3":"0","c1_name":"Alka Gupta","pt":"0","c4":"0","n":"2","name":"Menlo Park City School District, Governing Board Member","c2":"0","c5_name":"Scott Saywell","c2_name":"Caroline A. Lucas","p":"0","c5":"0","c4_name":"Scott Hinshaw","c3_name":"David Ackerman","c1":"0"},{"c3":"0","c1_name":"Andrea E. Gould","pt":"0","n":"2","c1_i":1,"name":"Pacifica School District, Governing Board Member","c2":"0","c2_name":"Connor Kessler","p":"0","c3_name":"Jesse D. Levin","c1":"0"},{"c3":"0","c1_name":"Marco A. Chávez","pt":"0","n":"2","c1_i":1,"name":"Ravenswood City School District, Governing Board Member","c3_i":1,"c2":"0","c2_name":"Marielena Gaona-Mendoza","p":"0","c3_name":"Sharifa Wilson","c1":"0"},{"c2_name":"Scott Allen Grindy","c1_name":"John C. Baker","pt":"0","p":"0","name":"South San Francisco Unified School District, Governing Board Member-2 yr","c2":"0","c1":"0"}],"Cities":[{"c3":"0","c1_name":"Braxton R. Lethco","pt":"0","c4":"0","n":"2","name":"Daly City, Council Member","c2":"0","c5_name":"Juslyn Manalo","c2_name":"Dana Claire Smith","p":"0","c5":"0","c4_name":"Glenn R. Sylvester","c3_name":"Gabriella Makstman","c1":"0"},{"c1_name":"K. Annette Hipona","pt":"0","p":"0","c1_i":1,"name":"Daly City, City Clerk","c1":"0"},{"c1_name":"Daneca Halvorson","pt":"0","p":"0","c1_i":1,"name":"Daly City, City Treasurer","c1":"0"},{"c3":"0","c1_name":"Carlos Romero","pt":"0","c4":"0","n":"3","c1_i":1,"name":"East Palo Alto, Council Member","c2":"0","c2_name":"Duane Goff","p":"0","c4_name":"Lisa Yarbrough-Gauthier","c3_name":"Larry James Moody","c1":"0","c4_i":1},{"c3":"0","c1_name":"Adam Eisen","pt":"0","c4":"0","n":"2","name":"Half Moon Bay, Council Member","c2":"0","c2_name":"Carol Joyce","p":"0","c4_name":"Michael Thompson","c3_name":"Harvey Rarback","c1":"0"},{"c3":"0","c1_name":"Catherine Carlton","pt":"0","n":"2","c1_i":1,"name":"Menlo Park, Council Member","c3_i":1,"c2":"0","c2_name":"Cecilia T. Taylor","p":"0","c3_name":"Ray Mueller","c1":"0"},{"c3":"0","c1_name":"Bridget Duffy","pt":"0","c4":"0","n":"2","name":"Pacifica, Council Member","c3_i":1,"c2":"0","c2_name":"Deirdre Martin","p":"0","c4_name":"Sue Vaterlaus","c3_name":"Mary Ann Nihart","c1":"0"},{"c3":"0","pt":"0","c4":"0","c2":"0","c5":"0","c3_name":"John Irish Goodwin","c1_name":"Barry B. Lazaro","n":"3","name":"Colma, Council Member","c2_i":1,"c5_i":1,"c2_name":"Diana Isabel Colvin","c5_name":"Raquel Gonzalez","p":"0","c4_name":"Laura Walsh","c1":"0"}],"County":[{"c1_name":"Sean Dabel","pt":"0","p":"0","name":"Superior Court Judge, Office #7","c1":"0"},{"c2_name":"Michael Guingona","c1_name":"David Canepa","pt":"0","p":"0","name":"Supervisor, 5th District","c2":"0","c1":"0"}],"Special Districts":[{"c3":"0","c1_name":"Kathryn Slater-Carter","pt":"0","n":"2","c1_i":1,"c2_i":1,"name":"Montara Water & Sanitary District, Member Board of Directors","c2":"0","c2_name":"Scott Boyd","p":"0","c3_name":"Thomas Peterson","c1":"0"},{"c3":"0","c1_name":"Frank Pagliaro","pt":"0","n":"2","c2_i":1,"name":"Peninsula Health Care District, Member Board of Directors","c2":"0","c2_name":"Ricardo Navarro","p":"0","c3_name":"Stephen Duncan","c1":"0"},{"c2_name":"Ed Larenas","c1_name":"Brian Rogers","pt":"0","p":"0","name":"San Mateo County Harbor District, Commissioner-2 yr","c2":"0","c1":"0"},{"c3":"0","c1_name":"Sabrina Brennan","pt":"0","c4":"0","n":"3","c1_i":1,"name":"San Mateo County Harbor District, Commissioner","c3_i":1,"c2":"0","c2_name":"Shawn Mooney","p":"0","c4_name":"Virginia Chang Kiraly","c3_name":"Tom Mattusch","c1":"0","c4_i":1},{"c3":"0","c1_name":"Harland Harrison","pt":"0","c4":"0","n":"2","c2_i":1,"name":"Sequoia Healthcare District, Member Board of Directors","c2":"0","c2_name":"Kathleen Kane","p":"0","c4_name":"Lois Garcia","c3_name":"Kim Griffin","c1":"0"},{"c2_name":"Brandon Kwan","c1_name":"Barbra A. Mathewson","pt":"0","p":"0","name":"Midcoast Community Council, Council Member-2 yr","c2":"0","c1":"0"}]},"Sonoma":{"Measures":[{"pt":"0","p":"0","No":"0","Yes":"0","a":"55%","name":"Measure C","d":null},{"pt":"0","p":"0","No":"0","Yes":"0","a":"55%","name":"Measure D","d":null},{"pt":"0","p":"0","No":"0","Yes":"0","a":"55%","name":"Measure E","d":null},{"pt":"0","p":"0","No":"0","Yes":"0","a":"55%","name":"Measure F","d":null},{"pt":"0","p":"0","No":"0","Yes":"0","a":"55%","name":"Measure G","d":null},{"pt":"0","p":"0","No":"0","Yes":"0","a":"66 2/3%","name":"Measure H","d":null},{"pt":"0","p":"0","No":"0","Yes":"0","a":"66 2/3%","name":"Measure I","d":null},{"pt":"0","p":"0","No":"0","Yes":"0","a":"66 2/3%","name":"Measure J","d":null},{"pt":"0","p":"0","No":"0","Yes":"0","a":"50% + 1","name":"Measure K","d":null},{"pt":"0","p":"0","No":"0","Yes":"0","a":"50% + 1","name":"Measure L","d":null},{"pt":"0","p":"0","No":"0","Yes":"0","a":"50% + 1","name":"Measure M","d":null},{"pt":"0","p":"0","No":"0","Yes":"0","a":"50% + 1","name":"Measure N","d":null},{"pt":"0","p":"0","No":"0","Yes":"0","a":"50% + 1","name":"Measure O","d":null},{"pt":"0","p":"0","No":"0","Yes":"0","a":"50% + 1","name":"Measure P","d":null},{"pt":"0","p":"0","No":"0","Yes":"0","a":"50% + 1","name":"Measure Q","d":null},{"pt":"0","p":"0","No":"0","Yes":"0","a":"50% + 1","name":"Measure R","d":null},{"pt":"0","p":"0","No":"0","Yes":"0","a":"66 2/3%","name":"Measure S","d":null},{"pt":"0","p":"0","No":"0","Yes":"0","a":"50% + 1","name":"Measure T","d":null},{"pt":"0","p":"0","No":"0","Yes":"0","a":"50% + 1","name":"Measure U","d":null},{"pt":"0","p":"0","No":"0","Yes":"0","a":"50% + 1","name":"Measure V","d":null},{"pt":"0","p":"0","No":"0","Yes":"0","a":"50% + 1","name":"Measure W","d":null},{"pt":"0","p":"0","No":"0","Yes":"0","a":"55%","name":"Measure X","d":null},{"pt":"0","p":"0","No":"0","Yes":"0","a":"66 2/3%","name":"Measure Y","d":null}],"School Districts":[{"c3":"0","pt":"0","c4":"0","c2":"0","c5":"0","c3_name":"Eric Higginbotham","c6_i":1,"c6_name":"Vickie Hegarty","c4_i":1,"c1_name":"Cecile F. Peters","n":"3","name":"Cloverdale Unified School District","c2_i":1,"c6":"0","c2_name":"Dianna Macdonald","c5_name":"Preston W. Addison","p":"0","c4_name":"Karen Scalabrini","c1":"0"},{"c3":"0","c1_name":"Chrissa Gillies","pt":"0","c4":"0","n":"2","c2_i":1,"name":"Cotati/Rohnert Park Unified School District","c2":"0","c2_name":"Jennifer Wiltermood","p":"0","c4_name":"Tom Nonn","c3_name":"Susan H. Adams","c1":"0"},{"c3":"0","pt":"0","c4":"0","c2":"0","c7":"0","c5":"0","c3_name":"Daniel Sebastian Novella","c6_i":1,"c6_name":"Julie Velasquez","c7_name":"Thomas K. Rackerby","c1_name":"Aracely Romo-Flores","n":"3","name":"Healdsburg Unified School District","c6":"0","c2_name":"Cindy Beth","c5_name":"Judith Sanderson","p":"0","c4_name":"Jami Sue Kiff","c1":"0"},{"c1_name":"Gary Desmet","pt":"0","c1_i":1,"name":"Sonoma Valley Unified School District","c2":"0","c2_name":"John Kelly","p":"0","c1":"0"},{"c3":"0","c1_name":"Bill Adams","pt":"0","n":"2","c1_i":1,"name":"Windsor Unified School District - 4 Year Full Term","c2":"0","c2_name":"George R. Valenzuela","p":"0","c3_name":"Mitchell Egan","c1":"0"},{"c1_name":"Alex Egan","pt":"0","c2_i":1,"name":"Windsor Unified School District - 2 Year Short Term","c2":"0","c2_name":"Esther Lemus","p":"0","c1":"0"},{"c3":"0","pt":"0","c4":"0","c2":"0","c5":"0","c3_name":"Evelyn Anderson","c6_name":"Laurie Fong","c4_i":1,"c1_name":"Caroline Bañuelos","n":"4","name":"City of Santa Rosa High School District","c6":"0","c5_i":1,"c2_name":"Ed Sheffield","c5_name":"Laura Gonzalez","p":"0","c4_name":"Jenni Klose","c1":"0"},{"c3":"0","c1_name":"Diane Landry","pt":"0","c4":"0","n":"2","c1_i":1,"name":"West Sonoma County Union High School District","c2":"0","c2_name":"Eric Kirchmann","p":"0","c4_name":"Ted Walker","c3_name":"Jeanne Bassett Fernandes","c1":"0","c4_i":1},{"c3":"0","pt":"0","c4":"0","c2":"0","c5":"0","c3_name":"Santiago F. Ortega","c4_i":1,"c1_name":"Adele Walker","n":"2","name":"Bellevue Union School District","c5_i":1,"c2_name":"Joy Bruce","c5_name":"Yvonne L. Kennedy","p":"0","c4_name":"Sharon Ligon","c1":"0"},{"c3":"0","c1_name":"Jean Bullard","pt":"0","n":"2","c1_i":1,"name":"Forestville Union School District","c3_i":1,"c2":"0","c2_name":"Josh Nultemeier","p":"0","c3_name":"Otho Vivian","c1":"0"},{"c3":"0","c1_name":"Desiree Beck","pt":"0","n":"2","c1_i":1,"name":"Gravenstein Union School District","c2":"0","c2_name":"Gregory Leon Appling","p":"0","c3_name":"Steve Schwartz","c1":"0"},{"c3":"0","c1_name":"Eurydice Rorick","pt":"0","n":"2","c1_i":1,"c2_i":1,"name":"Harmony Union School District","c2":"0","c2_name":"Henry E. Goff","p":"0","c3_name":"Mariah Lander","c1":"0"},{"c3":"0","c1_name":"Heather Burton","pt":"0","n":"2","name":"Old Adobe Union School District","c2":"0","c2_name":"Jonathan Lenz","p":"0","c3_name":"Marilyn Cohe","c1":"0"},{"c3":"0","c1_name":"Carol Lynn Wood","pt":"0","n":"2","c1_i":1,"name":"Rincon Valley Union School District","c2":"0","c2_name":"Lisa Brown","p":"0","c3_name":"Mike Cook","c1":"0"}],"Cities":[{"c3":"0","pt":"0","c4":"0","c2":"0","c5":"0","c3_name":"Don Taylor","c6_i":1,"c6_name":"Julie Combs","c4_i":1,"c1_name":"Brandi Asker","n":"4","name":"City of Santa Rosa, Council Member","c6":"0","c2_name":"Chris Rogers","c5_name":"Jack Tibbetts","p":"0","c4_name":"Ernesto Olivares","c1":"0"},{"c3":"0","pt":"0","c4":"0","c2":"0","c8_i":1,"c7":"0","c5":"0","c3_name":"Jason Turner","c6_name":"Melanie Bagby","c7_name":"Paula Wrenn","c1_name":"Alejandrina Crayford","n":"2","name":"City of Cloverdale, Council Member","c6":"0","c5_i":1,"c2_name":"James Luchini","c5_name":"Mary Ann Brigham","p":"0","c8_name":"Robert Cox","c4_name":"Keith King","c1":"0","c8":"0"},{"c3":"0","pt":"0","c4":"0","c2":"0","c5":"0","c3_name":"Jason Goebel","c6_i":1,"c6_name":"Wendy Skillman","c4_i":1,"c1_name":"Eris Weaver","n":"3","name":"City of Cotati, Council Member","c6":"0","c5_i":1,"c2_name":"George Barich","c5_name":"Susan Harvey","p":"0","c4_name":"John Dell'Osso","c1":"0"},{"c3":"0","pt":"0","c4":"0","c2":"0","c5":"0","c3_name":"Joe Naujokas","c6_name":"Tim Meinken","c1_name":"David Hagele","n":"3","name":"City of Healdsburg, Council Member","c2_i":1,"c6":"0","c5_i":1,"c2_name":"Gary W. Plass","c5_name":"Shaun F. McCaffery","p":"0","c4_name":"Mel Amato","c1":"0"},{"c3":"0","c1_name":"Bill Wolpert","pt":"0","c4":"0","n":"3","c2_i":1,"name":"City of Petaluma, Council Member","c3_i":1,"c2":"0","c2_name":"Gabe Kearney","p":"0","c4_name":"Mike Healy","c3_name":"Kathy Miller","c1":"0","c4_i":1},{"c3":"0","c1_name":"Jonathan Greenberg","pt":"0","n":"2","name":"City of Sebastopol, Council Member","c2":"0","c2_name":"Michael Anthony Carnacchi","p":"0","c3_name":"Neysa Hinton","c1":"0"},{"c3":"0","c1_name":"Amy Harrington","pt":"0","c4":"0","n":"2","c2_i":1,"name":"City of Sonoma, Council Member","c2":"0","c2_name":"David Cook","p":"0","c4_name":"Laurie Gallian","c3_name":"Jack Wagner","c1":"0","c4_i":1},{"c3":"0","c1_name":"Bruce G. Okrepkie","pt":"0","c4":"0","n":"2","c1_i":1,"name":"Town of Windsor, Council Member","c2":"0","c5_name":"Rosa Reynoza","c2_name":"Debora Fudge","p":"0","c5":"0","c4_name":"Michael Wall","c3_name":"Julia Donoho","c1":"0"}],"County":[{"c2_name":"Noreen Evans","c1_name":"Lynda Hopkins","pt":"0","p":"0","name":"Supervisor, District 5","c2":"0","c1":"0"},{"c1_name":"Gina Cuclis","pt":"0","c1_i":1,"name":"Board of Education, Trustee Area 1","c2":"0","c2_name":"Jason Carter","p":"0","c1":"0"}],"Special Districts":[{"c3":"0","c1_name":"Al Fiori","pt":"0","c4":"0","n":"3","c1_i":1,"c2_i":1,"name":"Gold Ridge Fire Protection District Director","c2":"0","c2_name":"Charlie Lachman","p":"0","c4_name":"Ronald L. Balzer","c3_name":"Joe Petersen","c1":"0","c4_i":1},{"c3":"0","c1_name":"Alice D. Petty-Hannum","pt":"0","n":"2","c1_i":1,"name":"Roseland Fire Protection District Director","c3_i":1,"c2":"0","c2_name":"Michael Hilber","p":"0","c3_name":"Sandra C. Bassignani","c1":"0"},{"c3":"0","c1_name":"Eira I. Klich-Heartt","pt":"0","c4":"0","n":"3","name":"Palm Drive Health Care District Director","c2":"0","c5_name":"Robert Cary","c2_name":"Gail G. Thomas","p":"0","c5":"0","c4_name":"Marsha Sue Lustig","c3_name":"Jim Horn","c1":"0","c4_i":1}],"College Districts":[{"c3":"0","c1_name":"Don Edgar","pt":"0","n":"2","c1_i":1,"name":"Sonoma County Junior College District - Santa Rosa Area","c3_i":1,"c2":"0","c2_name":"Mariana G. Martinez","p":"0","c3_name":"Richard W. Call","c1":"0"}]},"Marin":{"Measures":[{"pt":"0","p":"0","No":"0","Yes":"0","a":"66 2/3%","name":"Measure A","d":null},{"pt":"0","p":"0","No":"0","Yes":"0","a":"66 2/3%","name":"Measure B","d":null},{"pt":"0","p":"0","No":"0","Yes":"0","a":"50% + 1","name":"Measure C","d":null},{"pt":"0","p":"0","No":"0","Yes":"0","a":"66 2/3%","name":"Measure E","d":null},{"pt":"0","p":"0","No":"0","Yes":"0","a":"55%","name":"Measure G","d":null},{"pt":"0","p":"0","No":"0","Yes":"0","a":"66 2/3%","name":"Measure H","d":null},{"pt":"0","p":"0","No":"0","Yes":"0","a":"66 2/3%","name":"Measure K","d":null},{"pt":"0","p":"0","No":"0","Yes":"0","a":"66 2/3%","name":"Measure L","d":null},{"pt":"0","p":"0","No":"0","Yes":"0","a":"66 2/3%","name":"Measure M","d":null},{"pt":"0","p":"0","No":"0","Yes":"0","a":"66 2/3%","name":"Measure N","d":null},{"pt":"0","p":"0","No":"0","Yes":"0","a":"66 2/3%","name":"Measure O","d":null}],"School Districts":[{"c3":"0","c1_name":"Bob Demmerle","pt":"0","n":"2","c2_i":1,"name":"Bolinas-Stinson Union School District Governing Board Member","c2":"0","c2_name":"Cyrus Leben Harmon","p":"0","c3_name":"Georgia Woods","c1":"0"},{"c3":"0","c1_name":"Bill Ziegler","pt":"0","c4":"0","n":"2","c1_i":1,"c2_i":1,"name":"Sausalito Marin City School District Governing Board Member","c2":"0","c2_name":"Caroline F. Van Alst","p":"0","c4_name":"Debra Turner","c3_name":"David Suto","c1":"0"}],"Cities":[{"c3":"0","c1_name":"Joan Cox","pt":"0","c4":"0","n":"3","name":"City of Sausalito Member City Council","c3_i":1,"c2":"0","c2_name":"Joe Burns","p":"0","c4_name":"Sam Ruben","c3_name":"Ray Withy","c1":"0"}],"County":[{"c2_name":"Sheila Lichtblau","c1_name":"Michael Coffino","pt":"0","p":"0","name":"Superior Court Judge - Office 2","c2":"0","c1":"0"},{"c2_name":"Dominic Grossi","c1_name":"Dennis Rodoni","pt":"0","p":"0","name":"County Supervisor - District 4","c2":"0","c1":"0"}],"Special Districts":[{"c3":"0","c1_name":"Amber R. Distasi","pt":"0","n":"2","c1_i":1,"name":"Mesa Park Director","c2":"0","c2_name":"Nolan Godfrey","p":"0","c3_name":"Toby I. Nemec","c1":"0"},{"c3":"0","c1_name":"Cale Barrett Nichols","pt":"0","n":"2","c1_i":1,"c2_i":1,"name":"Strawberry Recreation District Director","c2":"0","c2_name":"Pamela G. Bohner","p":"0","c3_name":"Porter Davis","c1":"0"}]},"San Francisco":{"Measures":[{"pt":"597","p":"0","No":"0","Yes":"0","a":"55%","name":"Measure A","d":null},{"pt":"597","p":"0","No":"0","Yes":"0","a":"66 2/3%","name":"Measure B","d":null},{"pt":"597","p":"0","No":"0","Yes":"0","a":"66 2/3%","name":"Measure C","d":null},{"pt":"597","p":"0","No":"0","Yes":"0","a":"50% + 1","name":"Measure D","d":null},{"pt":"597","p":"0","No":"0","Yes":"0","a":"50% + 1","name":"Measure E","d":null},{"pt":"597","p":"0","No":"0","Yes":"0","a":"50% + 1","name":"Measure F","d":null},{"pt":"597","p":"0","No":"0","Yes":"0","a":"50% + 1","name":"Measure G","d":null},{"pt":"597","p":"0","No":"0","Yes":"0","a":"50% + 1","name":"Measure H","d":null},{"pt":"597","p":"0","No":"0","Yes":"0","a":"50% + 1","name":"Measure I","d":null},{"pt":"597","p":"0","No":"0","Yes":"0","a":"50% + 1","name":"Measure J","d":null},{"pt":"597","p":"0","No":"0","Yes":"0","a":"50% + 1","name":"Measure K","d":null},{"pt":"597","p":"0","No":"0","Yes":"0","a":"50% + 1","name":"Measure L","d":null},{"pt":"597","p":"0","No":"0","Yes":"0","a":"50% + 1","name":"Measure M","d":null},{"pt":"597","p":"0","No":"0","Yes":"0","a":"50% + 1","name":"Measure N","d":null},{"pt":"597","p":"0","No":"0","Yes":"0","a":"50% + 1","name":"Measure O","d":null},{"pt":"597","p":"0","No":"0","Yes":"0","a":"50% + 1","name":"Measure P","d":null},{"pt":"597","p":"0","No":"0","Yes":"0","a":"50% + 1","name":"Measure Q","d":null},{"pt":"597","p":"0","No":"0","Yes":"0","a":"50% + 1","name":"Measure R","d":null},{"pt":"597","p":"0","No":"0","Yes":"0","a":"66 2/3%","name":"Measure S","d":null},{"pt":"597","p":"0","No":"0","Yes":"0","a":"50% + 1","name":"Measure T","d":null},{"pt":"597","p":"0","No":"0","Yes":"0","a":"50% + 1","name":"Measure U","d":null},{"pt":"597","p":"0","No":"0","Yes":"0","a":"50% + 1","name":"Measure V","d":null},{"pt":"597","p":"0","No":"0","Yes":"0","a":"50% + 1","name":"Measure W","d":null},{"pt":"597","p":"0","No":"0","Yes":"0","a":"50% + 1","name":"Measure X","d":null}],"School Districts":[{"c3":"0","pt":"0","c4":"0","c9":"0","c2":"0","c7":"0","c5":"0","c3_name":"Mark Sanchez","c6_i":1,"c6_name":"Rachel Norton","c7_name":"Rob Geller","c4_i":1,"c1_name":"Ian Kalin","n":"4","name":"Board of Education","c2_i":1,"c6":"0","c2_name":"Jill Wynns","c5_name":"Phillip Kim","p":"0","c8_name":"Stevon Cook","c9_name":"Trevor McNeil","c4_name":"Matthew Haney","c1":"0","c8":"0"}],"County":[{"c3":"0","pt":"0","c4":"0","c9":"0","c10":"0","c2":"0","c10_name":"Sherman D'Silva","c7":"0","c5":"0","c3_name":"David E. Lee","c6_name":"Marjan Philhour","c7_name":"Richie Greenberg","c1_name":"Andy Thornley","name":"Board of Supervisors, District 1","c6":"0","c2_name":"Brian J. Larkin","c5_name":"Jonathan Lyens","p":"0","c8_name":"Samuel Kwong","c9_name":"Sandra Lee Fewer","c4_name":"Jason Jungreis","c1":"0","c8":"0"},{"c1_name":"Aaron Peskin","pt":"0","c1_i":1,"name":"Board of Supervisors, District 3","c2":"0","c2_name":"Tim E. Donnelly","p":"0","c1":"0"},{"c1_name":"Dean Preston","pt":"0","c2_i":1,"name":"Board of Supervisors, District 5","c2":"0","c2_name":"London Breed","p":"0","c1":"0"},{"c3":"0","c1_name":"Ben Matranga","pt":"0","c4":"0","name":"Board of Supervisors, District 7","c2":"0","c5_i":1,"c5_name":"Norman Yee","c2_name":"Joel Engardio","p":"0","c5":"0","c4_name":"Michael Young","c3_name":"John Farrell","c1":"0"},{"c3":"0","c1_name":"Hillary Ronen","pt":"0","c4":"0","name":"Board of Supervisors, District 9","c2":"0","c2_name":"Iswari Espana","p":"0","c4_name":"Melissa San Miguel","c3_name":"Joshua Arce","c1":"0"},{"c3":"0","c1_name":"Ahsha Safai","pt":"0","c4":"0","name":"Board of Supervisors, District 11","c2":"0","c5_name":"Magdalena De Guzman","c2_name":"Berta Hernandez","p":"0","c5":"0","c4_name":"Kimberly Alvarenga","c3_name":"Francisco Herrera","c1":"0"},{"c2_name":"Victor Hwang","c1_name":"Paul Henderson","pt":"0","p":"0","name":"Superior Court Judge, Office No. 7","c2":"0","c1":"0"}],"Special Districts":[{"c3":"0","c1_name":"Bevan Dufty","pt":"0","name":"BART Board of Directors, District 9","c2":"0","c2_name":"Gwyneth J. Borden","p":"0","c3_name":"Michael Petrelis","c1":"0"}],"College Districts":[{"c3":"0","pt":"0","c4":"0","c3_i":1,"c2":"0","c5":"0","c3_name":"Rafael Mandelman","c1_name":"Alex Randolph","n":"4","c1_i":1,"name":"Community College Board","c2_i":1,"c2_name":"Amy Bacharach","c5_name":"Tom Temprano","p":"0","c4_name":"Shanell Williams","c1":"0"}]},"Solano":{"Measures":[{"pt":"0","p":"0","No":"0","Yes":"0","a":"50% + 1","name":"Measure A","d":null},{"pt":"0","p":"0","No":"0","Yes":"0","a":"Advisory","name":"Measure B","d":null},{"pt":"0","p":"0","No":"0","Yes":"0","a":"50% + 1","name":"Measure C","d":null},{"pt":"0","p":"0","No":"0","Yes":"0","a":"55%","name":"Measure D","d":null},{"pt":"0","p":"0","No":"0","Yes":"0","a":"66 2/3%","name":"Measure H","d":null},{"pt":"0","p":"0","No":"0","Yes":"0","a":"50% + 1","name":"Measure K","d":null},{"pt":"0","p":"0","No":"0","Yes":"0","a":"50% + 1","name":"Measure L","d":null},{"pt":"0","p":"0","No":"0","Yes":"0","a":"50% + 1","name":"Measure M","d":null},{"pt":"0","p":"0","No":"0","Yes":"0","a":"50% + 1","name":"Measure N","d":null},{"pt":"0","p":"0","No":"0","Yes":"0","a":"50% + 1","name":"Measure O","d":null},{"pt":"0","p":"0","No":"0","Yes":"0","a":"50% + 1","name":"Measure P","d":null},{"pt":"0","p":"0","No":"0","Yes":"0","a":"55%","name":"Measure Q","d":null},{"pt":"0","p":"0","No":"0","Yes":"0","a":"50% + 1","name":"Measure S","d":null},{"pt":"0","p":"0","No":"0","Yes":"0","a":"50% + 1","name":"Measure T","d":null},{"pt":"0","p":"0","No":"0","Yes":"0","a":"50% + 1","name":"Measure V","d":null}],"School Districts":[{"c3":"0","c1_name":"Alan Fernandes","pt":"0","c4":"0","n":"2","c1_i":1,"name":"Davis Joint Unified School District","c2":"0","c2_name":"Bob Poppenga","p":"0","c4_name":"Susan Lovenburg","c3_name":"Jose J. Granda","c1":"0","c4_i":1},{"c3":"0","c1_name":"Bethany Smith","pt":"0","name":"Fairfield Unified School District, Trustee Area 1","c2":"0","c2_name":"Mike Wright","p":"0","c3_name":"Spencer Marks","c1":"0"},{"c2_name":"Melvin L. Cockhren, II","c1_name":"Joan K. Gaut","pt":"0","p":"0","name":"Fairfield Unified School District, Trustee Area 2","c2":"0","c1":"0"},{"c1_name":"Ana Petero","pt":"0","c2_i":1,"name":"Fairfield Unified School District, Trustee Area 6","c2":"0","c2_name":"John Silva","p":"0","c1":"0"},{"c1_name":"Elvia B. Coronado","pt":"0","c2_i":1,"name":"River Delta Unified School District, Trustee Area 1","c2":"0","c2_name":"Marilyn Riley","p":"0","c1":"0"},{"c1_name":"Don Olson","pt":"0","c1_i":1,"name":"River Delta Unified School District, Trustee Area 2","c2":"0","c2_name":"Donald Lopez","p":"0","c1":"0"},{"c3":"0","pt":"0","c4":"0","c2":"0","c7":"0","c5":"0","c3_name":"Jeanette McCree-Goudeau","c6_name":"Melissa Bandong Bowman","c7_name":"Sue Burton","c1_name":"Bob Lawson","n":"2","name":"Vallejo City Unified School District","c6":"0","c2_name":"Chidale O'Hara","c5_name":"Marianne Kearney-Brown","p":"0","c4_name":"John Fox","c1":"0"},{"c2_name":"Ruscal Cayangyang","c1_name":"Hazel A. Wilson","pt":"0","p":"0","name":"Vallejo City Unified School District Short Term ","c2":"0","c1":"0"}],"Cities":[{"c1_name":"Elizabeth Patterson","pt":"0","c1_i":1,"name":"City of Benicia, Mayor","c2":"0","c2_name":"Mark C. Hughes","p":"0","c1":"0"},{"c3":"0","pt":"0","c4":"0","c2":"0","c5":"0","c3_name":"Lionel Largaespada","c1_name":"Christina Strawbridge","n":"2","c1_i":1,"name":"City of Benicia, City Council","c5_i":1,"c2_name":"George Oakes","c5_name":"Tom Campbell","p":"0","c4_name":"Steve Young","c1":"0"},{"c3":"0","c1_name":"Jack M. Batchelor","pt":"0","name":"City of Dixon, Mayor","c2":"0","c2_name":"Loran Hoffmann","p":"0","c3_name":"Thom Bogue","c1":"0"},{"c2_name":"Steven C. Bird","c1_name":"Michael Loftin","pt":"0","p":"0","name":"City of Dixon, City Council, District 3","c2":"0","c1":"0"},{"c3":"0","c1_name":"Devon Minnema","pt":"0","name":"City of Dixon, City Council, District 4","c3_i":1,"c2":"0","c2_name":"Ginger K. Emerson","p":"0","c3_name":"Jerry Castañon, Sr.","c1":"0"},{"c2_name":"Wesley W. Atkinson","c1_name":"Michael J. Ceremello, Jr.","pt":"0","p":"0","name":"City of Dixon, City Treasurer","c2":"0","c1":"0"},{"c3":"0","c1_name":"Brian C. Thiemer","pt":"0","c4":"0","n":"2","c2_i":1,"name":"City of Fairfield, City Council","c3_i":1,"c2":"0","c2_name":"Pam Bertani","p":"0","c4_name":"Robert Marin","c3_name":"Rick Vaccaro","c1":"0"},{"c1_name":"Arvinda Krishnan","pt":"0","c2_i":1,"name":"City of Fairfield, City Treasurer","c2":"0","c2_name":"Oscar G. Reyes, Jr.","p":"0","c1":"0"},{"c3":"0","c1_name":"Arthur J. Darden","pt":"0","c4":"0","n":"2","name":"City of Rio Vista, City Council","c2":"0","c5_name":"Richard Gouveia","c2_name":"Don Roos","p":"0","c5":"0","c4_name":"Patrick Byron","c3_name":"Hope Cohn","c1":"0"},{"c3":"0","c1_name":"Alfonso Almendariz","pt":"0","n":"2","c2_i":1,"name":"City of Vacaville, City Council","c2":"0","c2_name":"Dilenna Harris","p":"0","c3_name":"Ron Rowlett","c1":"0"},{"c3":"0","c1_name":"Bill Pendergast","pt":"0","name":"City of Vallejo, Mayor","c2":"0","c2_name":"Bob Sampayan","p":"0","c3_name":"Landis Graden","c1":"0"},{"c3":"0","pt":"0","c4":"0","c2":"0","c7":"0","c7_i":1,"c5":"0","c3_name":"Latressa Wilson Alford","c6_i":1,"c6_name":"Robert H. McConnell","c7_name":"Rozzana Verder-Aliga","c1_name":"Guillermina Diaz","n":"3","name":"City of Vallejo, City Council","c6":"0","c2_name":"Hermie R. Sunga","c5_name":"Liat F. Meitzenheimer","p":"0","c8_name":"Vernon Williams, III","c4_name":"Lenesha Anderson","c1":"0","c8":"0"}],"County":[{"c2_name":"Monica Brown","c1_name":"Mike Ioakimedes","pt":"0","p":"0","name":"County Supervisor, District 2","c2":"0","c1":"0"},{"c2_name":"Betty Silva","c1_name":"Amy Sharp","pt":"0","p":"0","name":"Solano County Board of Education, Trustee Area 2","c2":"0","c1":"0"}],"Special Districts":[{"c1_name":"Bob Bishop","pt":"0","c1_i":1,"name":"Solano Irrigation District, Division 2","c2":"0","c2_name":"Lance Porter","p":"0","c1":"0"}],"College Districts":[{"c3":"0","c1_name":"Alvina Riley Sheeley","pt":"0","name":"Solano Community College District, Trustee Area 5","c2":"0","c2_name":"Chris Fickes","p":"0","c3_name":"Quinten Voyce","c1":"0"},{"c1_name":"Cecilia Escamilla-Greenwald","pt":"0","c2_i":1,"name":"Los Rios Community College District, Trustee Area 4","c2":"0","c2_name":"Ruth Scribner","p":"0","c1":"0"}]},"Napa":{"Measures":[{"pt":"0","p":"0","No":"0","Yes":"0","name":"Measure A","d":null},{"pt":"0","p":"0","No":"0","Yes":"0","name":"Measure B","d":null},{"pt":"0","p":"0","No":"0","Yes":"0","name":"Measure Z","d":null}],"School Districts":[{"c3":"0","c1_name":"Icela Martin","pt":"0","c4":"0","name":"Napa Valley Unified School District, Trustee Area No. 5","c2":"0","c2_name":"Jesse Ryan Allured","p":"0","c4_name":"Susan Larson Bouwer","c3_name":"Jessica Delasaux","c1":"0"}],"Cities":[{"c1_name":"Douglas Lloyd Lindsey","pt":"0","c2_i":1,"name":"American Canyon, Mayor","c2":"0","c2_name":"Leon Garcia","p":"0","c1":"0"},{"c3":"0","c1_name":"Anthony Heuschel","pt":"0","c4":"0","c2_i":1,"name":"American Canyon, City Council","c3_i":1,"c2":"0","c2_name":"Joan Bennett","p":"0","c4_name":"Mariam J. Aboudamous","c3_name":"Kenneth Leary","c1":"0"},{"c1_name":"Jill Techel","pt":"0","p":"0","c1_i":1,"name":"City of Napa, Mayor","c1":"0"},{"c3":"0","c1_name":"Doris Gentry","pt":"0","c2_i":1,"name":"City of Napa, City Council","c3_i":1,"c2":"0","c2_name":"Mary Luros","p":"0","c3_name":"Scott Sedgley","c1":"0"},{"c1_name":"Alan Galbraith","pt":"0","p":"0","c1_i":1,"name":"City of St. Helena, Mayor","c1":"0"},{"c3":"0","c1_name":"Geoff Ellsworth","pt":"0","c4":"0","c2_i":1,"name":"City of St. Helena, City Council","c2":"0","c2_name":"Gregory Jude Pitts","p":"0","c4_name":"Sharon Shaw Crull","c3_name":"Mary Koberstein","c1":"0","c4_i":1}],"County":[{"c1_name":"Mark Luce","pt":"0","c1_i":1,"name":"Supervisor, 2nd District","c2":"0","c2_name":"Ryan Gregory","p":"0","c1":"0"}],"College Districts":[{"c3":"0","c1_name":"Daniel Digardi","pt":"0","c1_i":1,"name":"Napa Valley College, Trustee Area No. 1","c2":"0","c2_name":"Jacqueline Kearns","p":"0","c3_name":"Jennifer Baker","c1":"0"},{"c2_name":"Rosaura Segura","c1_name":"Debbie Alter-Starr","pt":"0","p":"0","name":"Napa Valley College, Trustee Area No. 6","c2":"0","c1":"0"}]},"Alameda":{"Measures":[{"pt":"0","p":"0","No":"0","Yes":"0","a":"66 2/3%","name":"Measure A1","d":null},{"pt":"0","p":"0","No":"0","Yes":"0","a":"66 2/3%","name":"Measure B1","d":null},{"pt":"0","p":"0","No":"0","Yes":"0","a":"66 2/3%","name":"Measure E1","d":null},{"pt":"0","p":"0","No":"0","Yes":"0","a":"66 2/3%","name":"Measure G1","d":null},{"pt":"0","p":"0","No":"0","Yes":"0","a":"55%","name":"Measure H1","d":null},{"pt":"0","p":"0","No":"0","Yes":"0","a":"55%","name":"Measure I1","d":null},{"pt":"0","p":"0","No":"0","Yes":"0","a":"55% + 1","name":"Measure J1","d":null},{"pt":"0","p":"0","No":"0","Yes":"0","a":"66 2/3%","name":"Measure F1","d":null},{"pt":"0","p":"0","No":"0","Yes":"0","a":"50% + 1","name":"Measure K1","d":null},{"pt":"0","p":"0","No":"0","Yes":"0","a":"50% + 1","name":"Measure L1","d":null},{"pt":"0","p":"0","No":"0","Yes":"0","a":"50% + 1","name":"Measure M1","d":null},{"pt":"0","p":"0","No":"0","Yes":"0","a":"50% + 1","name":"Measure N1","d":null},{"pt":"0","p":"0","No":"0","Yes":"0","a":"50% + 1","name":"Measure O1","d":null},{"pt":"0","p":"0","No":"0","Yes":"0","a":"66 2/3%","name":"Measure P1","d":null},{"pt":"0","p":"0","No":"0","Yes":"0","a":"50% + 1","name":"Measure Q1","d":null},{"pt":"0","p":"0","No":"0","Yes":"0","a":"50% + 1","name":"Measure R1","d":null},{"pt":"0","p":"0","No":"0","Yes":"0","a":"50% + 1","name":"Measure S1","d":null},{"pt":"0","p":"0","No":"0","Yes":"0","a":"66 2/3%","name":"Measure T1","d":null},{"pt":"0","p":"0","No":"0","Yes":"0","a":"50% + 1","name":"Measure U1","d":null},{"pt":"0","p":"0","No":"0","Yes":"0","a":"50% + 1","name":"Measure V1","d":null},{"pt":"0","p":"0","No":"0","Yes":"0","a":"50% + 1","name":"Measure AA","d":null},{"pt":"0","p":"0","No":"0","Yes":"0","a":"50% + 1","name":"Measure BB","d":null},{"pt":"0","p":"0","No":"0","Yes":"0","a":"50% + 1","name":"Measure CC","d":null},{"pt":"0","p":"0","No":"0","Yes":"0","a":"50% + 1","name":"Measure DD","d":null},{"pt":"0","p":"0","No":"0","Yes":"0","a":"50% + 1","name":"Measure EE","d":null},{"pt":"0","p":"0","No":"0","Yes":"0","a":"50% + 1","name":"Measure FF","d":null},{"pt":"0","p":"0","No":"0","Yes":"0","a":"50% + 1","name":"Measure GG","d":null},{"pt":"0","p":"0","No":"0","Yes":"0","a":"50% + 1","name":"Measure II","d":null},{"pt":"0","p":"0","No":"0","Yes":"0","a":"50% + 1","name":"Measure JJ","d":null},{"pt":"0","p":"0","No":"0","Yes":"0","a":"66 2/3%","name":"Measure KK","d":null},{"pt":"0","p":"0","No":"0","Yes":"0","name":"Measure LL","d":null},{"pt":"0","p":"0","No":"0","Yes":"0","a":"50% + 1","name":"Measure MM","d":null},{"pt":"0","p":"0","No":"0","Yes":"0","a":"50% + 1","name":"Measure NN","d":null},{"pt":"0","p":"0","No":"0","Yes":"0","a":"50% + 1","name":"Measure OO","d":null},{"pt":"0","p":"0","No":"0","Yes":"0","a":"50% + 1","name":"Measure PP","d":null},{"pt":"0","p":"0","No":"0","Yes":"0","a":"66 2/3%","name":"Measure QQ","d":null},{"pt":"0","p":"0","No":"0","Yes":"0","a":"50% + 1","name":"Measure W1","d":null},{"pt":"0","p":"0","No":"0","Yes":"0","a":"50% + 1","name":"Measure X1","d":null},{"pt":"0","p":"0","No":"0","Yes":"0","a":"50% + 1","name":"Measure Y1","d":null},{"pt":"0","p":"0","No":"0","Yes":"0","a":"50% + 1","name":"Measure Z1","d":null}],"School Districts":[{"c3":"0","pt":"0","c4":"0","c2":"0","c5":"0","c3_name":"Dennis Popalardo","c6_name":"Matt Hettich","c4_i":1,"c1_name":"Anne McKereghan","n":"3","name":"Alameda Unified School District Governing Board Member","c6":"0","c2_name":"Ardella Dailey","c5_name":"Jennifer Williams","p":"0","c4_name":"Gray Harris","c1":"0"},{"c3":"0","c1_name":"Jo A.S. Loss","pt":"0","c4":"0","n":"3","c1_i":1,"name":"Castro Valley Unified School District Governing Board Members","c2":"0","c5_name":"Tojo Thomas","c2_name":"Lavender Whitaker","p":"0","c5":"0","c4_name":"Suresh C. Gupta","c3_name":"Monica Lee","c1":"0"},{"c3":"0","pt":"0","c4":"0","c2":"0","c5":"0","c3_name":"Gabrielle Blackman","c1_name":"Amy Miller","n":"3","c1_i":1,"name":"Dublin Unified School District Governing Board Members, Full Term","c2_i":1,"c2_name":"Dan Cunningham","c5_name":"Xiaozhao Zhuang","p":"0","c4_name":"Joe Giannini","c1":"0"},{"c1_name":"Dan Cherrier","pt":"0","c2_i":1,"name":"Dublin Unified School District Governing Board Member, Short Term","c2":"0","c2_name":"Sameer Hakim","p":"0","c1":"0"},{"c3":"0","c1_name":"Barbara Inch","pt":"0","n":"2","name":"Emery Unified School District Governing Board Members","c2":"0","c2_name":"Cruz J. Vargas","p":"0","c3_name":"Ken Bukowski","c1":"0"},{"c3":"0","pt":"0","c4":"0","c3_i":1,"c2":"0","c5":"0","c3_name":"Desrie Y. Campbell","c1_name":"Ann Crosbie","n":"3","c1_i":1,"name":"Fremont Unified School District Governing Board Members","c5_i":1,"c2_name":"Dax Choksi","c5_name":"Michele G. Berke","p":"0","c4_name":"Hiu Ng","c1":"0"},{"c3":"0","pt":"0","c4":"0","c2":"0","c7":"0","c5":"0","c3_name":"Joe Orlando Ramos","c6_name":"Robert Carlson","c7_name":"Todd E. Davis","c4_i":1,"c1_name":"Annette Walker","n":"3","c1_i":1,"name":"Hayward Unified School District Governing Board Members","c6":"0","c5_i":1,"c2_name":"Daniel Goldstein","c5_name":"Luis Reynoso","p":"0","c8_name":"Wynn Grcich","c4_name":"John I. Taylor","c1":"0","c8":"0"},{"c3":"0","pt":"0","c4":"0","c3_i":1,"c2":"0","c5":"0","c3_name":"David Anthony Pombo","c6_name":"Nagarjun Juturu","c1_name":"Anne Goodrich","n":"3","name":"Lammersville Joint Unified School District Governing Board Members","c6":"0","c5_i":1,"c2_name":"Corey Strock","c5_name":"Matthew D. Balzarini","p":"0","c4_name":"Lisa Boulais","c1":"0"},{"c3":"0","pt":"0","c4":"0","c2":"0","c5":"0","c3_name":"Lance Nishihira","c4_i":1,"c1_name":"Jeff Wang","n":"3","name":"New Haven Unified School District Governing Board Members","c2_i":1,"c2_name":"Jonas Dino","c5_name":"Sharan Kaur","p":"0","c4_name":"Michael Ritchie","c1":"0"},{"c3":"0","c1_name":"Jamie Yee Hintzke","pt":"0","c4":"0","n":"3","c1_i":1,"name":"Pleasanton Unified School District Governing Board Members","c2":"0","c2_name":"Kathleen Ruegsegger","p":"0","c4_name":"Valerie Arkin","c3_name":"Steve Maher","c1":"0","c4_i":1},{"c3":"0","c1_name":"Helen K. Foster","pt":"0","c4":"0","n":"3","c1_i":1,"name":"San Lorenzo Unified School District Governing Board Members","c2":"0","c2_name":"Kyla Sinegal","p":"0","c4_name":"Penny Peck","c3_name":"Marilyn Stewart","c1":"0","c4_i":1},{"c2_name":"Patricia Picard","c1_name":"Denie Kent-Romo","pt":"0","p":"0","name":"Sunol Glen Unified School District Governing Board Members","c2":"0","c1":"0"}],"Cities":[{"c3":"0","pt":"0","c4":"0","c2":"0","c5":"0","c3_name":"Malia Vella","c4_i":1,"c1_name":"Jennifer Roloff","n":"2","name":"City Council, Alameda","c5_i":1,"c2_name":"Lena Tam","c5_name":"Tony Daysog","p":"0","c4_name":"Marilyn Ezzy Ashcraft","c1":"0"},{"c1_name":"Kevin R. Kearney","pt":"0","c1_i":1,"name":"Auditor, Alameda","c2":"0","c2_name":"Mike McMahon","p":"0","c1":"0"},{"c1_name":"Jeff Bratzler","pt":"0","c2_i":1,"name":"Treasurer, Alameda","c2":"0","c2_name":"Kevin Kennedy","p":"0","c1":"0"},{"c3":"0","pt":"0","c4":"0","c3_i":1,"c2":"0","c5":"0","c3_name":"Michael Barnes","c4_i":1,"c1_name":"Amber Whitson","n":"3","name":"Member Of City Council,  Albany","c5_i":1,"c2_name":"Erik Giesen-Fields","c5_name":"Peter Maass","p":"0","c4_name":"Nick Pilch","c1":"0"},{"c3":"0","c1_name":"Clementina Duron","pt":"0","c4":"0","n":"2","name":"Members Of The Board Of Education, Albany","c2":"0","c2_name":"Jacob Clark","p":"0","c4_name":"Kim Trutane","c3_name":"Jon Raj Destin","c1":"0"},{"c1_name":"Kim Denton","pt":"0","p":"0","c1_i":1,"name":"City Treasurer, Albany","c1":"0"},{"c3":"0","pt":"0","c4":"0","c2":"0","c5":"0","c3_name":"Igor Tregub","c6_name":"Nate Wollman","c4_i":1,"c1_name":"Alejandro Soto-Vigil","n":"4","c1_i":1,"name":"Rent Stabilization Board Commissioners, Berkeley","c6":"0","c2_name":"Christina Murphy","c5_name":"Leah Simon-Weisberg","p":"0","c4_name":"Judy J. Hunt","c1":"0"},{"c3":"0","c1_name":"Abdur Sikder","pt":"0","n":"2","c2_i":1,"name":"School Directors, Berkeley","c3_i":1,"c2":"0","c2_name":"Beatriz Leyva-Cutler","p":"0","c3_name":"Judy Appel","c1":"0"},{"c1_name":"David G. Haubert","pt":"0","c1_i":1,"name":"Mayor, Dublin","c2":"0","c2_name":"Shawn Costello","p":"0","c1":"0"},{"c3":"0","pt":"0","c4":"0","c2":"0","c5":"0","c3_name":"Christian Patz","c6_name":"Louise Engel","c1_name":"Ally Medina","n":"3","name":"Members of City Council, Emeryville","c6":"0","c2_name":"Brynnda Collins","c5_name":"John J. Bauters","p":"0","c4_name":"John Van Geffen","c1":"0"},{"c3":"0","c1_name":"Arun Goel","pt":"0","c4":"0","n":"2","c2_i":1,"name":"Member Of City Council, Dublin","c2":"0","c2_name":"Doreen Wehrenberg","p":"0","c4_name":"Mona Lisa Ballesteros","c3_name":"Melissa Hernandez Strah","c1":"0"},{"c1_name":"Bill Harrison","pt":"0","c1_i":1,"name":"Mayor, Fremont","c2":"0","c2_name":"Lily Mei","p":"0","c1":"0"},{"c3":"0","pt":"0","c4":"0","c2":"0","c7":"0","c7_i":1,"c5":"0","c3_name":"Laurie Manuel","c6_name":"Rakesh Sharma","c7_name":"Vinnie Bacon","c1_name":"Cullen Tiernan","n":"2","name":"Member Of City Council, Fremont","c6":"0","c2_name":"Kathy Kimberlin","c5_name":"Raj Salwan","p":"0","c4_name":"Marty Froomin","c1":"0"},{"c1_name":"John P. Marchand","pt":"0","p":"0","c1_i":1,"name":"Mayor, Livermore","c1":"0"},{"c3":"0","pt":"0","c4":"0","c3_i":1,"c2":"0","c5":"0","c3_name":"Laureen Turner","c6_name":"Stewart W. Gary","c1_name":"Chester Moore","n":"2","name":"Member Of City Council, Livermore","c6":"0","c2_name":"John D. Stein","c5_name":"Robert J. Coomber, Jr.","p":"0","c4_name":"Robert Carling","c1":"0"},{"c1_name":"Alan L. Nagy","pt":"0","p":"0","c1_i":1,"name":"Mayor, Newark","c1":"0"},{"c1_name":"Luis L. Freitas","pt":"0","n":"2","c2_i":1,"name":"Member Of City Council, Newark","c2":"0","c2_name":"Maria Collazo","p":"0","c1":"0"},{"c3":"0","c1_name":"Bob McBain","pt":"0","c4":"0","n":"2","c1_i":1,"name":"Members of City Council, Piedmont","c3_i":1,"c2":"0","c2_name":"Jen Cavenaugh","p":"0","c4_name":"N. Bostrom-Fleming","c3_name":"Jonathan Levine","c1":"0"},{"c3":"0","pt":"0","c4":"0","c2":"0","c5":"0","c3_name":"Hari Titan","c1_name":"Andrea Swenson","n":"3","c1_i":1,"name":"Members of the Board of Education - Piedmont","c5_i":1,"c2_name":"Cory Smegal","c5_name":"Sarah Pearson","p":"0","c4_name":"Julie Caskey","c1":"0"},{"c1_name":"Jerry Thorne","pt":"0","c1_i":1,"name":"Mayor, Pleasanton","c2":"0","c2_name":"Julie Testa","p":"0","c1":"0"},{"c3":"0","c1_name":"Herb Ritter","pt":"0","n":"2","c2_i":1,"name":"Member Of City Council, Pleasanton","c3_i":1,"c2":"0","c2_name":"Jerry Pentin","p":"0","c3_name":"Karla Brown","c1":"0"},{"c1_name":"Carol Dutra-Vernaci","pt":"0","c1_i":1,"name":"Mayor, Union City","c2":"0","c2_name":"Jim Navarro","p":"0","c1":"0"},{"c3":"0","c1_name":"Gary Singh","pt":"0","name":"Member Of City Council, Union City","c2":"0","c2_name":"Jaime Patiño","p":"0","c3_name":"Lee Guio","c1":"0"},{"c3":"0","pt":"0","c4":"0","c2":"0","c7":"0","c5":"0","c3_name":"Guy Lee","c6_name":"Laurie Capitelli","c7_name":"Naomi D. Pete","c1_name":"Ben Gould","name":"Mayor, Berkeley","c6":"0","c2_name":"Bernt Rainer Wahl","c5_name":"Kriss Worthington","p":"0","c8_name":"Zachary Runningwolf","c4_name":"Jesse Arreguín","c1":"0","c8":"0"},{"c3":"0","c1_name":"Cheryl Davila","pt":"0","c2_i":1,"name":"Member Of City Council District #2, Berkeley","c2":"0","c2_name":"Darryl Moore","p":"0","c3_name":"Nanci Ira Armstrong-Temple","c1":"0"},{"c3":"0","c1_name":"Al G. Murray","pt":"0","c4":"0","name":"Member Of City Council District #3, Berkeley","c2":"0","c2_name":"Ben Bartlett","p":"0","c4_name":"Mark A. Coplan","c3_name":"Deborah Matthews","c1":"0"},{"c2_name":"Stephen Murphy","c1_name":"Sophie Hahn","pt":"0","p":"0","name":"Member Of City Council District #5, Berkeley","c2":"0","c1":"0"},{"c3":"0","c1_name":"Fred Dodsworth","pt":"0","name":"Member Of City Council District #6, Berkeley","c3_i":1,"c2":"0","c2_name":"Isabelle Gaston","p":"0","c3_name":"Susan Wengraf","c1":"0"},{"c3":"0","c1_name":"Bruce Quan","pt":"0","c4":"0","name":"Councilmember, At Large, Oakland","c2":"0","c5_i":1,"c5_name":"Rebecca Kaplan","c2_name":"Francis Hummel","p":"0","c5":"0","c4_name":"Peggy Moore","c3_name":"Nancy Sidebotham","c1":"0"},{"c1_name":"Dan Kalb","pt":"0","c1_i":1,"name":"Councilmember, District No. 1, Oakland","c2":"0","c2_name":"Kevin M. Corbett","p":"0","c1":"0"},{"c1_name":"Lynette Gibson McElhaney","pt":"0","c1_i":1,"name":"Councilmember, District No. 3, Oakland","c2":"0","c2_name":"Noni D. Session","p":"0","c1":"0"},{"c1_name":"Noel Gallo","pt":"0","c1_i":1,"name":"Councilmember, District No. 5, Oakland","c2":"0","c2_name":"Viola Gonzales","p":"0","c1":"0"},{"c3":"0","c1_name":"Larry E. Reid","pt":"0","c1_i":1,"name":"Councilmember, District No. 7, Oakland","c2":"0","c2_name":"Marcie Hodge","p":"0","c3_name":"Nehanda Imara","c1":"0"},{"c1_name":"Barbara J. Parker","pt":"0","p":"0","c1_i":1,"name":"City Attorney, Oakland","c1":"0"},{"c1_name":"Don Macleay","pt":"0","c2_i":1,"name":"School Director, District No. 1, Oakland","c2":"0","c2_name":"Jody London","p":"0","c1":"0"},{"c3":"0","c1_name":"Benjamin Lang","pt":"0","c4":"0","c2_i":1,"name":"School Director, District No. 3, Oakland","c2":"0","c2_name":"Jumoke Hinton Hodge","p":"0","c4_name":"Lucky Narain","c3_name":"Kharyshi Wiginton","c1":"0"},{"c3":"0","c1_name":"Huber Trenado","pt":"0","c4":"0","name":"School Director, District No. 5, Oakland","c2":"0","c2_name":"Mike Hassid","p":"0","c4_name":"Rosie Torres","c3_name":"Mike Hutchinson","c1":"0","c4_i":1},{"c1_name":"Chris Jackson","pt":"0","c2_i":1,"name":"School Director, District No. 7, Oakland","c2":"0","c2_name":"James Harris","p":"0","c1":"0"},{"c2_name":"Ed Hernandez","c1_name":"Bryan Azevedo","pt":"0","p":"0","name":"Member Of City Council #2, San Leandro","c2":"0","c1":"0"},{"c1_name":"Benny Lee","pt":"0","p":"0","c1_i":1,"name":"Member Of City Council #4, San Leandro","c1":"0"},{"c1_name":"Pete Ballew","pt":"0","p":"0","name":"Member Of City Council #6, San Leandro","c1":"0"}],"County":[{"c2_name":"Scott Jackson","c1_name":"Barbara Thomas","pt":"0","p":"0","name":"Superior Court Judge, Office #1","c2":"0","c1":"0"}],"Special Districts":[{"c1_name":"Greg Harper","pt":"0","c1_i":1,"name":"AC Transit District Director, District 2","c2":"0","c2_name":"Russ Tilleman","p":"0","c1":"0"},{"c3":"0","c1_name":"Aziz Akbari","pt":"0","c4":"0","n":"3","name":"Alameda County Water District Director","c2":"0","c2_name":"James Gunther","p":"0","c4_name":"Martin L. Koller","c3_name":"John Weed","c1":"0","c4_i":1},{"c1_name":"Jennifer Hosterman","pt":"0","c2_i":1,"name":"BART Board of Directors, District 5","c2":"0","c2_name":"John McPartland","p":"0","c1":"0"},{"c3":"0","c1_name":"Daniel M. Akagi","pt":"0","c4":"0","n":"3","c1_i":1,"c2_i":1,"name":"Castro Valley Sanitary District Directors","c2":"0","c2_name":"Dave Sadoff","p":"0","c4_name":"Timothy R. McGowan","c3_name":"John Maher","c1":"0","c4_i":1},{"c3":"0","c1_name":"Daniel Chesmore","pt":"0","name":"East Bay Regional Park District Director, Ward 4","c2":"0","c2_name":"Ellen M. Corbett","p":"0","c3_name":"Otis Lee Sanders","c1":"0"},{"c3":"0","c1_name":"Beth Wilson","pt":"0","n":"2","c1_i":1,"name":"Livermore Area Recreation & Park District Directors","c2":"0","c2_name":"Jan Palajac","p":"0","c3_name":"John Kibbe","c1":"0"},{"c3":"0","c1_name":"Dan Walters","pt":"0","n":"2","c1_i":1,"name":"Member, Board Of Directors, Oro Loma Sanitary District, Full Term","c3_i":1,"c2":"0","c2_name":"Diana Souza","p":"0","c3_name":"Roland J. Dias","c1":"0"},{"c1_name":"Chike Udemezue","pt":"0","c2_i":1,"name":"Member, Board Of Directors, Oro Loma Sanitary District, Short Term","c2":"0","c2_name":"Rita Duncan","p":"0","c1":"0"},{"c3":"0","c1_name":"Chitra Ramanathan","pt":"0","n":"2","c2_i":1,"name":"Washington Township Healthcare District Directors","c3_i":1,"c2":"0","c2_name":"Patricia Danielson","p":"0","c3_name":"William F. Nicholson","c1":"0"}],"College Districts":[{"c2_name":"Nick Resnick","c1_name":"Karen Weinstein","pt":"0","p":"0","name":"Peralta Community College District Trustee, Area 6","c2":"0","c1":"0"}]},"Special Districts":{"Measures":[{"pt":"0","p":"0","No":"0","Yes":"0","name":"Measure C1","d":null},{"pt":"597","p":"0","No":"0","Yes":"0","a":"66 2/3%","name":"Measure RR","d":null}],"School Districts":[{"c3":"0","c1_name":"Ellen Webster","pt":"0","n":"2","name":"Petaluma Joint Union High School District","c3_i":1,"c2":"0","c2_name":"Frank Lynch","p":"0","c3_name":"Mary S. Johnson","c1":"0"},{"c3":"0","pt":"0","c4":"0","c2":"0","c5":"0","c3_name":"Mark Galindo","c4_i":1,"c1_name":"Brian Fennen","n":"3","name":"Callistoga Joint Unified School District","c2_i":1,"c2_name":"Julie Elkeshen","c5_name":"Matthew Reid","p":"0","c4_name":"Martin Hunt","c1":"0"}],"Special Districts":[{"c1_name":"Dollene C. Jones","pt":"0","c2_i":1,"name":"AC Transit District Director, At-large","c2":"0","c2_name":"H. E. Christian Peeples","p":"0","c1":"0"},{"c3":"0","c1_name":"Lateefah Simon","pt":"0","c4":"0","name":"BART Board of Directors, District 7","c2":"0","c2_name":"Roland Emerson","p":"0","c4_name":"Zakhary Mallett","c3_name":"Will Roscoe","c1":"0","c4_i":1},{"c3":"0","c1_name":"Ken Chew","pt":"0","c4":"0","c2_i":1,"name":"BART Board of Directors, District 3","c2":"0","c2_name":"Rebecca Saltzman","p":"0","c4_name":"Worth Freeman","c3_name":"Varun Paul","c1":"0"},{"c3":"0","c1_name":"Audree V. Jones-Taylor","pt":"0","c4":"0","name":"East Bay Regional Park District Director, Ward 2","c2":"0","c2_name":"Dee Rosario","p":"0","c4_name":"Kent Fickett","c3_name":"John Roberts","c1":"0"}],"College Districts":[{"c1_name":"Edralin J. Maduli","pt":"0","c2_i":1,"name":"Chabot - Las Positas Community College District Trustee, Area 7","c2":"0","c2_name":"William Macedo","p":"0","c1":"0"},{"c3":"0","c1_name":"C. Jennet Stebbins","pt":"0","c1_i":1,"name":"San Joaquin Delta Community College District Trustee, Area 1","c2":"0","c2_name":"LeJames Dillion-Melton","p":"0","c3_name":"Robert L. Duran","c1":"0"},{"c1_name":"Carlos A. Huerta","pt":"0","c2_i":1,"name":"San Joaquin Delta Community College District Trustee, Area 2","c2":"0","c2_name":"Claudia Y. Moreno-Rabago","p":"0","c1":"0"},{"c1_name":"Juan Ensastegui Lopez","pt":"0","c2_i":1,"name":"San Joaquin Delta Community College District Trustee, Area 6","c2":"0","c2_name":"Teresa R. Brown","p":"0","c1":"0"}]}}